Workbook
Name UPDATE: 'Data Sheet'!$E$1

Sheet ASSUMPTIONS
G3: ASSUMPTIONS
B5: 1 | C5: TAX RATE IS CONSIDERED TO 27.00% FOR ALL FIRMS
B6: 2 | C6: FOR FORECASTING OF PROFIT & LOSS, BALANCE SHEET, CASH FLOW I AM USING FORECAST FUNCTIONS OF EXCEL
B7: 3 | C7: LEVERED BETA FOR ALL FIRMS IS TAKEN FROM GOOGLE (5 YEAR MONTHLY)
B8: 4 | C8: THE PRE TAX COST OF DEBT IS CALCULATED BY DIVIDING THE INTEREST EXPENSE OF LAST HISTORICAL YEAR FROM PROFIT & LOSS TO CURRENT TOTAL DEBT OF COMPANY
B9: 5 | C9: RISK FREE RATE ON 10-YEAR GOVERNMENT OF INDIA BOND YIELD IS APPROXIMATLY 6.75%.
B10: 6 | C10: INFY ANNUAL AVERAGE RETURN IS 5.73%
B11: 7 | C11: IN NET CAPEX I AM ONLY CONSIDERING FIXED ASSESTS PURCHASED BECAUSE THERE IS DATA AVAILABLE FOR FIXED ASSESTS SOLD
B12: 8 | C12: MARGINAL TAX RATE IS CONSIDERED TO 25.00%
B13: 9 | C13: TERMINAL GROWTH IS 5.75%

Sheet FINANCIAL MODEL<

Sheet Profit & Loss
A1: ='Data Sheet'!B1 -> INFOSYS LTD | H1: =UPDATE
A3: Narration | B3: ='Data Sheet'!B16 -> 42825 | C3: ='Data Sheet'!C16 -> 43190 | D3: ='Data Sheet'!D16 -> 43555 | E3: ='Data Sheet'!E16 -> 43921 | F3: ='Data Sheet'!F16 -> 44286 | G3: ='Data Sheet'!G16 -> 44651 | H3: ='Data Sheet'!H16 -> 45016 | I3: ='Data Sheet'!I16 -> 45382 | ... K3: ='Data Sheet'!K16 -> 46112 | L3: 46473 | M3: 46840 | N3: 47206 | O3: 47572 | P3: 47938
A4: Sales | B4: =IFERROR('Data Sheet'!B17,0) -> 68484 | C4: =IFERROR('Data Sheet'!C17,0) -> 70522 | D4: =IFERROR('Data Sheet'!D17,0) -> 82675 | E4: =IFERROR('Data Sheet'!E17,0) -> 90791 | F4: =IFERROR('Data Sheet'!F17,0) -> 100472 | G4: =IFERROR('Data Sheet'!G17,0) -> 121641 | H4: =IFERROR('Data Sheet'!H17,0) -> 146767 | I4: =IFERROR('Data Sheet'!I17,0) -> 153670 | ... K4: =IFERROR('Data Sheet'!K17,0) -> 178650 | L4: =IFERROR(FORECASTING!D15,0) -> 190427.6 | M4: =IFERROR(FORECASTING!D16,0) -> 203656.95 | N4: =IFERROR(FORECASTING!D17,0) -> 216886.29 | O4: =IFERROR(FORECASTING!D18,0) -> 230115.64 | P4: =IFERROR(FORECASTING!D19,0) -> 243344.98
A6: Expenses | B6: =IFERROR(SUM('Data Sheet'!B18,'Data Sheet'!B20:B22, -1*'Data Sheet'!B19),0) -> 44609 | C6: =IFERROR(SUM('Data Sheet'!C18,'Data Sheet'!C20:C22, -1*'Data Sheet'!C19),0) -> 46395 | D6: =IFERROR(SUM('Data Sheet'!D18,'Data Sheet'!D20:D22, -1*'Data Sheet'!D19),0) -> 55446 | E6: =IFERROR(SUM('Data Sheet'!E18,'Data Sheet'!E20:E22, -1*'Data Sheet'!E19),0) -> 62210 | F6: =IFERROR(SUM('Data Sheet'!F18,'Data Sheet'!F20:F22, -1*'Data Sheet'!F19),0) -> 68490 | G6: =IFERROR(SUM('Data Sheet'!G18,'Data Sheet'!G20:G22, -1*'Data Sheet'!G19),0) -> 84819 | H6: =IFERROR(SUM('Data Sheet'!H18,'Data Sheet'!H20:H22, -1*'Data Sheet'!H19),0) -> 104880 | I6: =IFERROR(SUM('Data Sheet'!I18,'Data Sheet'!I20:I22, -1*'Data Sheet'!I19),0) -> 110030 | ... K6: =IFERROR(SUM('Data Sheet'!K18,'Data Sheet'!K20:K22, -1*'Data Sheet'!K19),0) -> 128257 | L6: =IFERROR(FORECASTING!D36,0) -> 137552.8 | M6: =IFERROR(FORECASTING!D37,0) -> 147622.02 | N6: =IFERROR(FORECASTING!D38,0) -> 157691.24 | O6: =IFERROR(FORECASTING!D39,0) -> 167760.45 | P6: =IFERROR(FORECASTING!D40,0) -> 177829.67
A8: GROSS MARGIN | B8: =IFERROR(B4-B6,0) -> 23875 | C8: =IFERROR(C4-C6,0) -> 24127 | D8: =IFERROR(D4-D6,0) -> 27229 | E8: =IFERROR(E4-E6,0) -> 28581 | F8: =IFERROR(F4-F6,0) -> 31982 | G8: =IFERROR(G4-G6,0) -> 36822 | H8: =IFERROR(H4-H6,0) -> 41887 | I8: =IFERROR(I4-I6,0) -> 43640 | ... P8: =IFERROR(P4-P6,0) -> 65515.309
A9: Other Income | B9: =IFERROR('Data Sheet'!B25,0) -> 3050 | C9: =IFERROR('Data Sheet'!C25,0) -> 3311 | D9: =IFERROR('Data Sheet'!D25,0) -> 2882 | E9: =IFERROR('Data Sheet'!E25,0) -> 2803 | F9: =IFERROR('Data Sheet'!F25,0) -> 2201 | G9: =IFERROR('Data Sheet'!G25,0) -> 2295 | H9: =IFERROR('Data Sheet'!H25,0) -> 2701 | I9: =IFERROR('Data Sheet'!I25,0) -> 4711 | ... K9: =IFERROR('Data Sheet'!K25,0) -> 3033 | L9: =IFERROR(FORECASTING!I36,0) -> 3418.8 | M9: =IFERROR(FORECASTING!I37,0) -> 3484.2727 | N9: =IFERROR(FORECASTING!I38,0) -> 3549.7455 | O9: =IFERROR(FORECASTING!I39,0) -> 3615.2182 | P9: =IFERROR(FORECASTING!I40,0) -> 3680.6909
A11: NET MARGIN | B11: =IFERROR(B8+B9,0) -> 26925 | C11: =IFERROR(C8+C9,0) -> 27438 | D11: =IFERROR(D8+D9,0) -> 30111 | E11: =IFERROR(E8+E9,0) -> 31384 | F11: =IFERROR(F8+F9,0) -> 34183 | G11: =IFERROR(G8+G9,0) -> 39117 | H11: =IFERROR(H8+H9,0) -> 44588 | I11: =IFERROR(I8+I9,0) -> 48351 | ... P11: =IFERROR(P8+P9,0) -> 69196
A12: SG&A | B12: =IFERROR(SUM('Data Sheet'!B23:B24),0) -> 5271 | C12: =IFERROR(SUM('Data Sheet'!C23:C24),0) -> 5305 | D12: =IFERROR(SUM('Data Sheet'!D23:D24),0) -> 7059 | E12: =IFERROR(SUM('Data Sheet'!E23:E24),0) -> 6314 | F12: =IFERROR(SUM('Data Sheet'!F23:F24),0) -> 4093 | G12: =IFERROR(SUM('Data Sheet'!G23:G24),0) -> 5331 | H12: =IFERROR(SUM('Data Sheet'!H23:H24),0) -> 6757 | I12: =IFERROR(SUM('Data Sheet'!I23:I24),0) -> 7215 | ... K12: =IFERROR(SUM('Data Sheet'!K23:K24),0) -> 8113 | L12: =IFERROR(FORECASTING!N36,0) -> 7661.8 | M12: =IFERROR(FORECASTING!N37,0) -> 7916.1818 | N12: =IFERROR(FORECASTING!N38,0) -> 8170.5636 | O12: =IFERROR(FORECASTING!N39,0) -> 8424.9455 | P12: =IFERROR(FORECASTING!N40,0) -> 8679.3273
A14: EBITDA | B14: =IFERROR(B11-B12,0) -> 21654 | C14: =IFERROR(C11-C12,0) -> 22133 | D14: =IFERROR(D11-D12,0) -> 23052 | E14: =IFERROR(E11-E12,0) -> 25070 | F14: =IFERROR(F11-F12,0) -> 30090 | G14: =IFERROR(G11-G12,0) -> 33786 | H14: =IFERROR(H11-H12,0) -> 37831 | I14: =IFERROR(I11-I12,0) -> 41136 | ... P14: =IFERROR(P11-P12,0) -> 60516.673
A15: Depreciation | B15: =IFERROR('Data Sheet'!B26,0) -> 1703 | C15: =IFERROR('Data Sheet'!C26,0) -> 1863 | D15: =IFERROR('Data Sheet'!D26,0) -> 2011 | E15: =IFERROR('Data Sheet'!E26,0) -> 2893 | F15: =IFERROR('Data Sheet'!F26,0) -> 3267 | G15: =IFERROR('Data Sheet'!G26,0) -> 3476 | H15: =IFERROR('Data Sheet'!H26,0) -> 4225 | I15: =IFERROR('Data Sheet'!I26,0) -> 4678 | ... K15: =IFERROR('Data Sheet'!K26,0) -> 4902 | L15: =IFERROR(FORECASTING!N56,0) -> 5615.4667 | M15: =FORECASTING!N57 -> 6021.3697 | N15: =FORECASTING!N58 -> 6427.2727 | O15: =FORECASTING!N59 -> 6833.1758 | P15: =FORECASTING!N60 -> 7239.0788
A16: Interest | B16: =IFERROR('Data Sheet'!B27,0) -> 0 | C16: =IFERROR('Data Sheet'!C27,0) -> 0 | D16: =IFERROR('Data Sheet'!D27,0) -> 0 | E16: =IFERROR('Data Sheet'!E27,0) -> 170 | F16: =IFERROR('Data Sheet'!F27,0) -> 195 | G16: =IFERROR('Data Sheet'!G27,0) -> 200 | H16: =IFERROR('Data Sheet'!H27,0) -> 284 | I16: =IFERROR('Data Sheet'!I27,0) -> 470 | ... K16: =IFERROR('Data Sheet'!K27,0) -> 416 | L16: =FORECASTING!D56 -> 526.86667 | M16: =IFERROR(FORECASTING!D57,0) -> 583.55152 | N16: =IFERROR(FORECASTING!D58,0) -> 640.23636 | O16: =IFERROR(FORECASTING!D59,0) -> 696.92121 | P16: =IFERROR(FORECASTING!D60,0) -> 753.60606
A18: Profit before tax | B18: =IFERROR('Data Sheet'!B28,0) -> 19951 | C18: =IFERROR('Data Sheet'!C28,0) -> 20270 | D18: =IFERROR('Data Sheet'!D28,0) -> 21041 | E18: =IFERROR('Data Sheet'!E28,0) -> 22007 | F18: =IFERROR('Data Sheet'!F28,0) -> 26628 | G18: =IFERROR('Data Sheet'!G28,0) -> 30110 | H18: =IFERROR('Data Sheet'!H28,0) -> 33322 | I18: =IFERROR('Data Sheet'!I28,0) -> 35988 | ... K18: =IFERROR('Data Sheet'!K28,0) -> 39995 | L18: =IFERROR(L14-L15-L16,0) -> 42489.467 | M18: =IFERROR(M14-M15-M16,0) -> 44998.097 | N18: =IFERROR(N14-N15-N16,0) -> 47506.727 | O18: =IFERROR(O14-O15-O16,0) -> 50015.358 | P18: =IFERROR(P14-P15-P16,0) -> 52523.988
A19: Tax | B19: =IFERROR('Data Sheet'!B29,0) -> 5598 | C19: =IFERROR('Data Sheet'!C29,0) -> 4241 | D19: =IFERROR('Data Sheet'!D29,0) -> 5631 | E19: =IFERROR('Data Sheet'!E29,0) -> 5368 | F19: =IFERROR('Data Sheet'!F29,0) -> 7205 | G19: =IFERROR('Data Sheet'!G29,0) -> 7964 | H19: =IFERROR('Data Sheet'!H29,0) -> 9214 | I19: =IFERROR('Data Sheet'!I29,0) -> 9740 | ... K19: =IFERROR('Data Sheet'!K29,0) -> 10521 | L19: =IFERROR(FORECASTING!I56,0) -> 11749.6 | M19: =IFERROR(FORECASTING!I57,0) -> 12497.891 | N19: =IFERROR(FORECASTING!I58,0) -> 13246.182 | O19: =IFERROR(FORECASTING!I59,0) -> 13994.473 | P19: =IFERROR(FORECASTING!I60,0) -> 14742.764
A21: Net profit | B21: =IFERROR(B18-B19,0) -> 14353 | C21: =IFERROR(C18-C19,0) -> 16029 | D21: =IFERROR(D18-D19,0) -> 15410 | E21: =IFERROR(E18-E19,0) -> 16639 | F21: =IFERROR(F18-F19,0) -> 19423 | G21: =IFERROR(G18-G19,0) -> 22146 | H21: =IFERROR(H18-H19,0) -> 24108 | I21: =IFERROR(I18-I19,0) -> 26248 | ... P21: =IFERROR(P18-P19,0) -> 37781.224
A23: NO. OF EQUITY SHARE | B23: =IFERROR('Data Sheet'!B93,0) -> 459.39 | C23: =IFERROR('Data Sheet'!C93,0) -> 436.82 | D23: =IFERROR('Data Sheet'!D93,0) -> 436.89 | E23: =IFERROR('Data Sheet'!E93,0) -> 425.9 | F23: =IFERROR('Data Sheet'!F93,0) -> 426.07 | G23: =IFERROR('Data Sheet'!G93,0) -> 420.67 | H23: =IFERROR('Data Sheet'!H93,0) -> 414.86 | I23: =IFERROR('Data Sheet'!I93,0) -> 415.09 | ... K23: =IFERROR('Data Sheet'!K93,0) -> 405.56 | L23: =IFERROR(L21/L25,0) -> 406.67057 | M23: =IFERROR(M21/M25,0) -> 404.9314 | N23: =IFERROR(N21/N25,0) -> 403.38358 | O23: =IFERROR(O21/O25,0) -> 401.99715 | P23: =IFERROR(P21/P25,0) -> 400.74813
A25: EPS | B25: =IFERROR(B21/B23,0) -> 31.243606 | C25: =IFERROR(C21/C23,0) -> 36.694748 | D25: =IFERROR(D21/D23,0) -> 35.272036 | E25: =IFERROR(E21/E23,0) -> 39.067856 | F25: =IFERROR(F21/F23,0) -> 45.586406 | G25: =IFERROR(G21/G23,0) -> 52.644591 | H25: =IFERROR(H21/H23,0) -> 58.11117 | I25: =IFERROR(I21/I23,0) -> 63.234479 | ... K25: =IFERROR(K21/K23,0) -> 72.67482 | L25: =IFERROR(FORECASTING!N15,0) -> 75.589111 | M25: =IFERROR(FORECASTING!N16,0) -> 80.261016 | N25: =IFERROR(FORECASTING!N17,0) -> 84.932921 | O25: =IFERROR(FORECASTING!N18,0) -> 89.604826 | P25: =IFERROR(FORECASTING!N19,0) -> 94.276732
A27: EPS GROWTH% | C27: =IFERROR(C25/B25-1,0) -> 0.17447227 | D27: =IFERROR(D25/C25-1,0) -> -0.038771542 | E27: =IFERROR(E25/D25-1,0) -> 0.10761556 | F27: =IFERROR(F25/E25-1,0) -> 0.16685199 | G27: =IFERROR(G25/F25-1,0) -> 0.15483091 | H27: =IFERROR(H25/G25-1,0) -> 0.10383933 | I27: =IFERROR(I25/H25-1,0) -> 0.088163932 | J27: =IFERROR(J25/I25-1,0) -> 0.018536361 | ... P27: =IFERROR(P25/O25-1,0) -> 0.05213899
A28: Price to earning | B28: =IF(B29>0,B29/B25,"") -> 16.359507 | C28: =IF(C29>0,C29/C25,"") -> 15.421825 | D28: =IF(D29>0,D29/D25,"") -> 21.088944 | E28: =IF(E29>0,E29/E25,"") -> 16.420148 | F28: =IF(F29>0,F29/F25,"") -> 30.010043 | G28: =IF(G29>0,G29/G25,"") -> 36.221195 | H28: =IF(H29>0,H29/H25,"") -> 24.572728 | I28: =IF(I29>0,I29/I25,"") -> 23.690398 | ... P28: =IF(P29>0,P29/P25,"") -> 24.614334
A29: Price | B29: =IFERROR('Data Sheet'!B90,0) -> 511.13 | C29: =IFERROR('Data Sheet'!C90,0) -> 565.9 | D29: =IFERROR('Data Sheet'!D90,0) -> 743.85 | E29: =IFERROR('Data Sheet'!E90,0) -> 641.5 | F29: =IFERROR('Data Sheet'!F90,0) -> 1368.05 | G29: =IFERROR('Data Sheet'!G90,0) -> 1906.85 | H29: =IFERROR('Data Sheet'!H90,0) -> 1427.95 | I29: =IFERROR('Data Sheet'!I90,0) -> 1498.05 | ... K29: =IFERROR('Data Sheet'!K90,0) -> 1250.6 | L29: =IFERROR(FORECASTING!D76,0) -> 1827.0407 | M29: =IFERROR(FORECASTING!D77,0) -> 1950.4202 | N29: =IFERROR(FORECASTING!D78,0) -> 2073.7998 | O29: =IFERROR(FORECASTING!D79,0) -> 2197.1794 | P29: =IFERROR(FORECASTING!D80,0) -> 2320.559
A31: RATIOS:
A32: DIVIDEND PER SHARE | B32: =IFERROR('Data Sheet'!B31/'Profit & Loss'!B23,0) -> 12.824833 | C32: =IFERROR('Data Sheet'!C31/'Profit & Loss'!C23,0) -> 21.669337 | D32: =IFERROR('Data Sheet'!D31/'Profit & Loss'!D23,0) -> 21.109433 | E32: =IFERROR('Data Sheet'!E31/'Profit & Loss'!E23,0) -> 17.438366 | F32: =IFERROR('Data Sheet'!F31/'Profit & Loss'!F23,0) -> 26.91952 | G32: =IFERROR('Data Sheet'!G31/'Profit & Loss'!G23,0) -> 30.92115 | H32: =IFERROR('Data Sheet'!H31/'Profit & Loss'!H23,0) -> 33.913127 | I32: =IFERROR('Data Sheet'!I31/'Profit & Loss'!I23,0) -> 45.901371 | ... K32: =IFERROR('Data Sheet'!K31/'Profit & Loss'!K23,0) -> 47.91005 | L32: =IFERROR(L37/L23,0) -> 51.769684 | M32: =IFERROR(M37/M23,0) -> 55.748788 | N32: =IFERROR(N37/N23,0) -> 59.733874 | O32: =IFERROR(O37/O23,0) -> 63.724064 | P32: =IFERROR(P37/P23,0) -> 67.718645
A33: OPM | B33: =IF(B8>0,B8/B4,0) -> 0.34862158 | C33: =IF(C8>0,C8/C4,0) -> 0.34212019 | D33: =IF(D8>0,D8/D4,0) -> 0.32934986 | E33: =IF(E8>0,E8/E4,0) -> 0.31479993 | F33: =IF(F8>0,F8/F4,0) -> 0.31831754 | G33: =IF(G8>0,G8/G4,0) -> 0.30271043 | H33: =IF(H8>0,H8/H4,0) -> 0.28539794 | I33: =IF(I8>0,I8/I4,0) -> 0.28398516 | ... P33: =IF(P8>0,P8/P4,0) -> 0.26922811
A34: DIVIDEND PAYOUT RATIO | B34: =IFERROR(B32/B25,0) -> 0.41047865 | C34: =IFERROR(C32/C25,0) -> 0.59052966 | D34: =IFERROR(D32/D25,0) -> 0.59847502 | E34: =IFERROR(E32/E25,0) -> 0.44636096 | F34: =IFERROR(F32/F25,0) -> 0.5905164 | G34: =IFERROR(G32/G25,0) -> 0.58735663 | H34: =IFERROR(H32/H25,0) -> 0.58359051 | I34: =IFERROR(I32/I25,0) -> 0.7258915 | ... P34: =IFERROR(P32/P25,0) -> 0.71829649
A35: RETAINED EARNINGS | B35: =IFERROR(1-B34,0) -> 0.58952135 | C35: =IFERROR(1-C34,0) -> 0.40947034 | D35: =IFERROR(1-D34,0) -> 0.40152498 | E35: =IFERROR(1-E34,0) -> 0.55363904 | F35: =IFERROR(1-F34,0) -> 0.4094836 | G35: =IFERROR(1-G34,0) -> 0.41264337 | H35: =IFERROR(1-H34,0) -> 0.41640949 | I35: =IFERROR(1-I34,0) -> 0.2741085 | ... P35: =IFERROR(1-P34,0) -> 0.28170351
A37: DIVIDEND AMOUNT | B37: =IFERROR('Data Sheet'!B31,0) -> 5891.6 | C37: =IFERROR('Data Sheet'!C31,0) -> 9465.6 | D37: =IFERROR('Data Sheet'!D31,0) -> 9222.5 | E37: =IFERROR('Data Sheet'!E31,0) -> 7427 | F37: =IFERROR('Data Sheet'!F31,0) -> 11469.6 | G37: =IFERROR('Data Sheet'!G31,0) -> 13007.6 | H37: =IFERROR('Data Sheet'!H31,0) -> 14069.2 | I37: =IFERROR('Data Sheet'!I31,0) -> 19053.2 | ... K37: =IFERROR('Data Sheet'!K31,0) -> 19430.4 | L37: =IFERROR(FORECASTING!I76,0) -> 21053.207 | M37: =IFERROR(FORECASTING!I77,0) -> 22574.435 | N37: =IFERROR(FORECASTING!I78,0) -> 24095.664 | O37: =IFERROR(FORECASTING!I79,0) -> 25616.892 | P37: =IFERROR(FORECASTING!I80,0) -> 27138.121
A58: EXPENSES % REVENUE | B58: =IFERROR(B6/B4,0) -> 0.65137842 | C58: =IFERROR(C6/C4,0) -> 0.65787981 | D58: =IFERROR(D6/D4,0) -> 0.67065014 | E58: =IFERROR(E6/E4,0) -> 0.68520007 | F58: =IFERROR(F6/F4,0) -> 0.68168246 | G58: =IFERROR(G6/G4,0) -> 0.69728957 | H58: =IFERROR(H6/H4,0) -> 0.71460206 | I58: =IFERROR(I6/I4,0) -> 0.71601484 | ... P58: =IFERROR(P6/P4,0) -> 0.73077189
A59: EBITDA MARGIN | B59: =IFERROR(B14/B4,0) -> 0.31619064 | C59: =IFERROR(C14/C4,0) -> 0.31384532 | D59: =IFERROR(D14/D4,0) -> 0.27882673 | E59: =IFERROR(E14/E4,0) -> 0.27612869 | F59: =IFERROR(F14/F4,0) -> 0.29948642 | G59: =IFERROR(G14/G4,0) -> 0.27775174 | H59: =IFERROR(H14/H4,0) -> 0.2577623 | I59: =IFERROR(I14/I4,0) -> 0.26769051 | ... P59: =IFERROR(P14/P4,0) -> 0.24868675
A60: GROSS MARGIN % | B60: =IFERROR(B11/B4,0) -> 0.39315753 | C60: =IFERROR(C11/C4,0) -> 0.38907008 | D60: =IFERROR(D11/D4,0) -> 0.36420925 | E60: =IFERROR(E11/E4,0) -> 0.34567303 | F60: =IFERROR(F11/F4,0) -> 0.34022414 | G60: =IFERROR(G11/G4,0) -> 0.32157743 | H60: =IFERROR(H11/H4,0) -> 0.30380126 | I60: =IFERROR(I11/I4,0) -> 0.31464176 | ... P60: =IFERROR(P11/P4,0) -> 0.28435351
A61: SG&A % | B61: =IFERROR(B12/B4,0) -> 0.076966883 | C61: =IFERROR(C12/C4,0) -> 0.075224753 | D61: =IFERROR(D12/D4,0) -> 0.085382522 | E61: =IFERROR(E12/E4,0) -> 0.069544338 | F61: =IFERROR(F12/F4,0) -> 0.040737718 | G61: =IFERROR(G12/G4,0) -> 0.043825684 | H61: =IFERROR(H12/H4,0) -> 0.04603896 | I61: =IFERROR(I12/I4,0) -> 0.046951259 | ... P61: =IFERROR(P12/P4,0) -> 0.035666761
A62: PROBIT BEFORE TAX % | B62: =IFERROR(B18/B4,0) -> 0.29132352 | C62: =IFERROR(C18/C4,0) -> 0.28742804 | D62: =IFERROR(D18/D4,0) -> 0.25450257 | E62: =IFERROR(E18/E4,0) -> 0.24239187 | F62: =IFERROR(F18/F4,0) -> 0.26502906 | G62: =IFERROR(G18/G4,0) -> 0.24753167 | H62: =IFERROR(H18/H4,0) -> 0.22704014 | I62: =IFERROR(I18/I4,0) -> 0.23419015 | ... P62: =IFERROR(P18/P4,0) -> 0.21584167
A63: NET PROFIT% | B63: =IFERROR(B21/B4,0) -> 0.2095818 | C63: =IFERROR(C21/C4,0) -> 0.22729077 | D63: =IFERROR(D21/D4,0) -> 0.1863925 | E63: =IFERROR(E21/E4,0) -> 0.18326706 | F63: =IFERROR(F21/F4,0) -> 0.19331754 | G63: =IFERROR(G21/G4,0) -> 0.18206033 | H63: =IFERROR(H21/H4,0) -> 0.16426036 | I63: =IFERROR(I21/I4,0) -> 0.17080757 | ... P63: =IFERROR(P21/P4,0) -> 0.15525787

Sheet Balance Sheet
A1: ='Profit & Loss'!A1 -> INFOSYS LTD | E1: =UPDATE | J1: SCREENER.IN
A3: Narration | B3: ='Data Sheet'!B56 -> 42825 | C3: ='Data Sheet'!C56 -> 43190 | D3: ='Data Sheet'!D56 -> 43555 | E3: ='Data Sheet'!E56 -> 43921 | F3: ='Data Sheet'!F56 -> 44286 | G3: ='Data Sheet'!G56 -> 44651 | H3: ='Data Sheet'!H56 -> 45016 | I3: ='Data Sheet'!I56 -> 45382 | ... K3: ='Data Sheet'!K56 -> 46112 | L3: 46473 | M3: 46840 | N3: 47206 | O3: 47572 | P3: 47938
A4: Equity Share Capital | B4: =IFERROR('Data Sheet'!B57,0) -> 1144 | C4: =IFERROR('Data Sheet'!C57,0) -> 1088 | D4: =IFERROR('Data Sheet'!D57,0) -> 2170 | E4: =IFERROR('Data Sheet'!E57,0) -> 2122 | F4: =IFERROR('Data Sheet'!F57,0) -> 2124 | G4: =IFERROR('Data Sheet'!G57,0) -> 2098 | H4: =IFERROR('Data Sheet'!H57,0) -> 2069 | I4: =IFERROR('Data Sheet'!I57,0) -> 2071 | ... K4: =IFERROR('Data Sheet'!K57,0) -> 2024 | L4: =IFERROR(FORECASTING!N76,0) -> 2369.4667 | M4: =IFERROR(FORECASTING!N77,0) -> 2455.1333 | N4: =IFERROR(FORECASTING!N78,0) -> 2540.8 | O4: =IFERROR(FORECASTING!N79,0) -> 2626.4667 | P4: =IFERROR(FORECASTING!N80,0) -> 2712.1333
A5: Reserves | B5: =IFERROR('Data Sheet'!B58,0) -> 67838 | C5: =IFERROR('Data Sheet'!C58,0) -> 63835 | D5: =IFERROR('Data Sheet'!D58,0) -> 62778 | E5: =IFERROR('Data Sheet'!E58,0) -> 63328 | F5: =IFERROR('Data Sheet'!F58,0) -> 74227 | G5: =IFERROR('Data Sheet'!G58,0) -> 73252 | H5: =IFERROR('Data Sheet'!H58,0) -> 73338 | I5: =IFERROR('Data Sheet'!I58,0) -> 86045 | ... K5: =IFERROR('Data Sheet'!K58,0) -> 90828 | L5: =IFERROR(FORECASTING!D96,0) -> 93643.733 | M5: =IFERROR(FORECASTING!D97,0) -> 97047.794 | N5: =IFERROR(FORECASTING!D98,0) -> 100451.85 | O5: =IFERROR(FORECASTING!D99,0) -> 103855.92 | P5: =IFERROR(FORECASTING!D100,0) -> 107259.98
A6: Borrowings | B6: =IFERROR('Data Sheet'!B59,0) -> 0 | C6: =IFERROR('Data Sheet'!C59,0) -> 0 | D6: =IFERROR('Data Sheet'!D59,0) -> 0 | E6: =IFERROR('Data Sheet'!E59,0) -> 4633 | F6: =IFERROR('Data Sheet'!F59,0) -> 5325 | G6: =IFERROR('Data Sheet'!G59,0) -> 5474 | H6: =IFERROR('Data Sheet'!H59,0) -> 8299 | I6: =IFERROR('Data Sheet'!I59,0) -> 8359 | ... K6: =IFERROR('Data Sheet'!K59,0) -> 9176 | L6: =IFERROR(FORECASTING!I96,0) -> 11386.467 | M6: =IFERROR(FORECASTING!I97,0) -> 12556.861 | N6: =IFERROR(FORECASTING!I98,0) -> 13727.255 | O6: =IFERROR(FORECASTING!I99,0) -> 14897.648 | P6: =IFERROR(FORECASTING!I100,0) -> 16068.042
A7: Other Liabilities | B7: =IFERROR('Data Sheet'!B60,0) -> 14166 | C7: =IFERROR('Data Sheet'!C60,0) -> 14426 | D7: =IFERROR('Data Sheet'!D60,0) -> 19118 | E7: =IFERROR('Data Sheet'!E60,0) -> 21717 | F7: =IFERROR('Data Sheet'!F60,0) -> 25835 | G7: =IFERROR('Data Sheet'!G60,0) -> 35905 | H7: =IFERROR('Data Sheet'!H60,0) -> 40890 | I7: =IFERROR('Data Sheet'!I60,0) -> 39545 | ... K7: =IFERROR('Data Sheet'!K60,0) -> 52260 | L7: =IFERROR(FORECASTING!$N96,0) -> 54689.133 | M7: =IFERROR(FORECASTING!N97,0) -> 59039.667 | N7: =IFERROR(FORECASTING!N98,0) -> 63390.2 | O7: =IFERROR(FORECASTING!N99,0) -> 67740.733 | P7: =IFERROR(FORECASTING!$N100,0) -> 72091.267
A8: TOTAL LIABILITIES | B8: =IFERROR('Data Sheet'!B61,0) -> 83148 | C8: =IFERROR('Data Sheet'!C61,0) -> 79349 | D8: =IFERROR('Data Sheet'!D61,0) -> 84066 | E8: =IFERROR('Data Sheet'!E61,0) -> 91800 | F8: =IFERROR('Data Sheet'!F61,0) -> 107511 | G8: =IFERROR('Data Sheet'!G61,0) -> 116729 | H8: =IFERROR('Data Sheet'!H61,0) -> 124596 | I8: =IFERROR('Data Sheet'!I61,0) -> 136020 | ... K8: =IFERROR('Data Sheet'!K61,0) -> 154288 | L8: =IFERROR(SUM(L4:L7),0) -> 162088.8 | M8: =IFERROR(SUM(M4:M7),0) -> 171099.45 | N8: =IFERROR(SUM(N4:N7),0) -> 180110.11 | O8: =IFERROR(SUM(O4:O7),0) -> 189120.76 | P8: =IFERROR(SUM(P4:P7),0) -> 198131.42
A10: FIXED ASSESTS NET BLOCK | B10: =IFERROR('Data Sheet'!B62,0) -> 14179 | C10: =IFERROR('Data Sheet'!C62,0) -> 12574 | D10: =IFERROR('Data Sheet'!D62,0) -> 15710 | E10: =IFERROR('Data Sheet'!E62,0) -> 23789 | F10: =IFERROR('Data Sheet'!F62,0) -> 25505 | G10: =IFERROR('Data Sheet'!G62,0) -> 25800 | H10: =IFERROR('Data Sheet'!H62,0) -> 29225 | I10: =IFERROR('Data Sheet'!I62,0) -> 27622 | ... K10: =IFERROR('Data Sheet'!K62,0) -> 33770 | L10: =IFERROR(FORECASTING!D116,0) -> 36619.867 | M10: =IFERROR(FORECASTING!D117,0) -> 38930.115 | N10: =IFERROR(FORECASTING!D118,0) -> 41240.364 | O10: =IFERROR(FORECASTING!D119,0) -> 43550.612 | P10: =IFERROR(FORECASTING!D120,0) -> 45860.861
A11: Capital Work in Progress | B11: =IFERROR('Data Sheet'!B63,0) -> 1365 | C11: =IFERROR('Data Sheet'!C63,0) -> 1606 | D11: =IFERROR('Data Sheet'!D63,0) -> 1388 | E11: =IFERROR('Data Sheet'!E63,0) -> 954 | F11: =IFERROR('Data Sheet'!F63,0) -> 922 | G11: =IFERROR('Data Sheet'!G63,0) -> 416 | H11: =IFERROR('Data Sheet'!H63,0) -> 288 | I11: =IFERROR('Data Sheet'!I63,0) -> 293 | ... K11: =IFERROR('Data Sheet'!K63,0) -> 526
A12: Investments | B12: =IFERROR('Data Sheet'!B64,0) -> 16423 | C12: =IFERROR('Data Sheet'!C64,0) -> 12163 | D12: =IFERROR('Data Sheet'!D64,0) -> 11261 | E12: =IFERROR('Data Sheet'!E64,0) -> 8792 | F12: =IFERROR('Data Sheet'!F64,0) -> 14205 | G12: =IFERROR('Data Sheet'!G64,0) -> 20324 | H12: =IFERROR('Data Sheet'!H64,0) -> 19478 | I12: =IFERROR('Data Sheet'!I64,0) -> 24623 | ... K12: =IFERROR('Data Sheet'!K64,0) -> 21880 | L12: =IFERROR(FORECASTING!I116,0) -> 25060.533 | M12: =IFERROR(FORECASTING!I117,0) -> 26477.176 | N12: =IFERROR(FORECASTING!I118,0) -> 27893.818 | O12: =IFERROR(FORECASTING!I119,0) -> 29310.461 | P12: =IFERROR(FORECASTING!I120,0) -> 30727.103
A13: Other Assets | B13: =IFERROR('Data Sheet'!B65-SUM('Data Sheet'!B67:B69),0) -> 16234 | C13: =IFERROR('Data Sheet'!C65-SUM('Data Sheet'!C67:C69),0) -> 20046 | D13: =IFERROR('Data Sheet'!D65-SUM('Data Sheet'!D67:D69),0) -> 21312 | E13: =IFERROR('Data Sheet'!E65-SUM('Data Sheet'!E67:E69),0) -> 21129 | F13: =IFERROR('Data Sheet'!F65-SUM('Data Sheet'!F67:F69),0) -> 22871 | G13: =IFERROR('Data Sheet'!G65-SUM('Data Sheet'!G67:G69),0) -> 30019 | H13: =IFERROR('Data Sheet'!H65-SUM('Data Sheet'!H67:H69),0) -> 38008 | I13: =IFERROR('Data Sheet'!I65-SUM('Data Sheet'!I67:I69),0) -> 38503 | ... K13: =IFERROR('Data Sheet'!K65-SUM('Data Sheet'!K67:K69),0) -> 40677 | L13: =IFERROR(FORECASTING!N116,0) -> 44615.4 | M13: =IFERROR(FORECASTING!N117,0) -> 47533.382 | N13: =IFERROR(FORECASTING!N118,0) -> 50451.364 | O13: =IFERROR(FORECASTING!N119,0) -> 53369.345 | P13: =IFERROR(FORECASTING!N120,0) -> 56287.327
A14: TOTAL NON CURRENT ASSESTS | B14: =IFERROR(SUM(B10:B13),0) -> 48201 | C14: =IFERROR(SUM(C10:C13),0) -> 46389 | D14: =IFERROR(SUM(D10:D13),0) -> 49671 | E14: =IFERROR(SUM(E10:E13),0) -> 54664 | F14: =IFERROR(SUM(F10:F13),0) -> 63503 | G14: =IFERROR(SUM(G10:G13),0) -> 76559 | H14: =IFERROR(SUM(H10:H13),0) -> 86999 | I14: =IFERROR(SUM(I10:I13),0) -> 91041 | ... P14: =IFERROR(SUM(P10:P13),0) -> 132875.29
A16: Receivables | B16: =IFERROR('Data Sheet'!B67,0) -> 12322 | C16: =IFERROR('Data Sheet'!C67,0) -> 13142 | D16: =IFERROR('Data Sheet'!D67,0) -> 14827 | E16: =IFERROR('Data Sheet'!E67,0) -> 18487 | F16: =IFERROR('Data Sheet'!F67,0) -> 19294 | G16: =IFERROR('Data Sheet'!G67,0) -> 22698 | H16: =IFERROR('Data Sheet'!H67,0) -> 25424 | I16: =IFERROR('Data Sheet'!I67,0) -> 30193 | ... K16: =IFERROR('Data Sheet'!K67,0) -> 35234 | L16: 0 | M16: 0 | N16: 0 | O16: 0 | P16: 0
A17: Inventory | B17: =IFERROR('Data Sheet'!B68,0) -> 0 | C17: =IFERROR('Data Sheet'!C68,0) -> 0 | D17: =IFERROR('Data Sheet'!D68,0) -> 0 | E17: =IFERROR('Data Sheet'!E68,0) -> 0 | F17: =IFERROR('Data Sheet'!F68,0) -> 0 | G17: =IFERROR('Data Sheet'!G68,0) -> 0 | H17: =IFERROR('Data Sheet'!H68,0) -> 0 | I17: =IFERROR('Data Sheet'!I68,0) -> 0 | ... K17: =IFERROR('Data Sheet'!K68,0) -> 0 | L17: 0 | M17: 0 | N17: 0 | O17: 0 | P17: 0
A18: Cash & Bank | B18: =IFERROR('Data Sheet'!B69,0) -> 22625 | C18: =IFERROR('Data Sheet'!C69,0) -> 19818 | D18: =IFERROR('Data Sheet'!D69,0) -> 19568 | E18: =IFERROR('Data Sheet'!E69,0) -> 18649 | F18: =IFERROR('Data Sheet'!F69,0) -> 24714 | G18: =IFERROR('Data Sheet'!G69,0) -> 17472 | H18: =IFERROR('Data Sheet'!H69,0) -> 12173 | I18: =IFERROR('Data Sheet'!I69,0) -> 14786 | ... K18: =IFERROR('Data Sheet'!K69,0) -> 22201 | L18: =IFERROR(FORECASTING!D136,0) -> 18914.867 | M18: =IFERROR(FORECASTING!D137,0) -> 18781.915 | N18: =IFERROR(FORECASTING!D138,0) -> 18648.964 | O18: =IFERROR(FORECASTING!D139,0) -> 18516.012 | P18: =IFERROR(FORECASTING!D140,0) -> 18383.061
A19: TOTAL CURRENT ASSESTS | B19: =IFERROR(SUM(B16:B18),0) -> 34947 | C19: =IFERROR(SUM(C16:C18),0) -> 32960 | D19: =IFERROR(SUM(D16:D18),0) -> 34395 | E19: =IFERROR(SUM(E16:E18),0) -> 37136 | F19: =IFERROR(SUM(F16:F18),0) -> 44008 | G19: =IFERROR(SUM(G16:G18),0) -> 40170 | H19: =IFERROR(SUM(H16:H18),0) -> 37597 | I19: =IFERROR(SUM(I16:I18),0) -> 44979 | ... P19: =IFERROR(SUM(P16:P18),0) -> 18383.061
A22: TOTAL ASSESTS | B22: =IFERROR(B14+B19,0) -> 83148 | C22: =IFERROR(C14+C19,0) -> 79349 | D22: =IFERROR(D14+D19,0) -> 84066 | E22: =IFERROR(E14+E19,0) -> 91800 | F22: =IFERROR(F14+F19,0) -> 107511 | G22: =IFERROR(G14+G19,0) -> 116729 | H22: =IFERROR(H14+H19,0) -> 124596 | I22: =IFERROR(I14+I19,0) -> 136020 | ... P22: =IFERROR(P14+P19,0) -> 151258.35
A24: CHECK | B24: =B22=B8 -> TRUE | C24: =C22=C8 -> TRUE | D24: =D22=D8 -> TRUE | E24: =E22=E8 -> TRUE | F24: =F22=F8 -> TRUE | G24: =G22=G8 -> TRUE | H24: =H22=H8 -> TRUE | I24: =I22=I8 -> TRUE | ... P24: =P22=P8 -> FALSE

Sheet Cash Flow
A1: ='Balance Sheet'!A1 -> INFOSYS LTD | E1: =UPDATE | J1: SCREENER.IN
A3: Narration | B3: ='Data Sheet'!B81 -> 42825 | C3: ='Data Sheet'!C81 -> 43190 | D3: ='Data Sheet'!D81 -> 43555 | E3: ='Data Sheet'!E81 -> 43921 | F3: ='Data Sheet'!F81 -> 44286 | G3: ='Data Sheet'!G81 -> 44651 | H3: ='Data Sheet'!H81 -> 45016 | I3: ='Data Sheet'!I81 -> 45382 | ... K3: ='Data Sheet'!K81 -> 46112 | L3: 46473 | M3: 46840 | N3: 47206 | O3: 47572 | P3: 47938
A5: CASH FROM OPERATING ACTIVITIES | B5: =IFERROR('Data Sheet'!B82,0) -> 11531 | C5: =IFERROR('Data Sheet'!C82,0) -> 13218 | D5: =IFERROR('Data Sheet'!D82,0) -> 14841 | E5: =IFERROR('Data Sheet'!E82,0) -> 17003 | F5: =IFERROR('Data Sheet'!F82,0) -> 23224 | G5: =IFERROR('Data Sheet'!G82,0) -> 23885 | H5: =IFERROR('Data Sheet'!H82,0) -> 22467 | I5: =IFERROR('Data Sheet'!I82,0) -> 25210 | ... K5: =IFERROR('Data Sheet'!K82,0) -> 33986 | L5: =IFERROR(FORECASTING!I136,0) -> 36383.4 | M5: =IFERROR(FORECASTING!I137,0) -> 38979.309 | N5: =IFERROR(FORECASTING!I138,0) -> 41575.218 | O5: =IFERROR(FORECASTING!I139,0) -> 44171.127 | P5: =IFERROR(FORECASTING!I140,0) -> 46767.036
A7: CASH FLOW FROM INVESTING ACTIVITIES | B7: =IFERROR('Data Sheet'!B83,0) -> -14664 | C7: =IFERROR('Data Sheet'!C83,0) -> 4533 | D7: =IFERROR('Data Sheet'!D83,0) -> -632 | E7: =IFERROR('Data Sheet'!E83,0) -> -331 | F7: =IFERROR('Data Sheet'!F83,0) -> -7373 | G7: =IFERROR('Data Sheet'!G83,0) -> -6485 | H7: =IFERROR('Data Sheet'!H83,0) -> -1071 | I7: =IFERROR('Data Sheet'!I83,0) -> -5093 | ... K7: =IFERROR('Data Sheet'!K83,0) -> 3546 | L7: {=TRANSPOSE(FORECASTING!N136:N140)} -> 239.06667 | M7: 817.69697 | N7: 1396.3273 | O7: 1974.9576 | P7: 2553.5879
A9: CASH FLOW FROM FINANCING ACTIVITIES | B9: =IFERROR('Data Sheet'!B84,0) -> -6939 | C9: =IFERROR('Data Sheet'!C84,0) -> -20505 | D9: =IFERROR('Data Sheet'!D84,0) -> -14512 | E9: =IFERROR('Data Sheet'!E84,0) -> -17591 | F9: =IFERROR('Data Sheet'!F84,0) -> -9786 | G9: =IFERROR('Data Sheet'!G84,0) -> -24642 | H9: =IFERROR('Data Sheet'!H84,0) -> -26695 | I9: =IFERROR('Data Sheet'!I84,0) -> -17504 | ... K9: =IFERROR('Data Sheet'!K84,0) -> -39786 | L9: {=TRANSPOSE(FORECASTING!D156:D160)} -> -32823.533 | M9: -35116.521 | N9: -37409.509 | O9: -39702.497 | P9: -41995.485
A13: NET CASH FLOW | B13: =IFERROR(SUM(B5:B9),0) -> -10072 | C13: =IFERROR(SUM(C5:C9),0) -> -2754 | D13: =IFERROR(SUM(D5:D9),0) -> -303 | E13: =IFERROR(SUM(E5:E9),0) -> -919 | F13: =IFERROR(SUM(F5:F9),0) -> 6065 | G13: =IFERROR(SUM(G5:G9),0) -> -7242 | H13: =IFERROR(SUM(H5:H9),0) -> -5299 | I13: =IFERROR(SUM(I5:I9),0) -> 2613 | ... P13: =IFERROR(SUM(P5:P9),0) -> 7325.1394
H28: =IFERROR(SUM(#REF!),0) -> 0 | I28: =IFERROR(SUM(#REF!),0) -> 0 | J28: =IFERROR(SUM(#REF!),0) -> 0 | K28: =IFERROR(SUM(#REF!),0) -> 0

Sheet RATIO ANALYSIS
G1: RATIO ANALYSIS | T1: LAST 10 HISTORICAL YEARS
C3: 42825 | D3: 43190 | E3: 43555 | F3: 43921 | G3: 44286 | H3: 44651 | I3: 45016 | J3: 45382 | K3: 45747 | L3: 46112 | M3: 46473 | N3: 46840 | O3: 47206 | P3: 47572 | Q3: 47938 | T3: TREND | U3: MEAN | V3: MEDIAN
B4: SALES GROWTH | C4: - | D4: =IFERROR(Annual[[#This Row],[Column3]]/Annual[[#This Row],[Column2]]-1,0) -> 0.029758776 | E4: =IFERROR(Annual[[#This Row],[Column4]]/Annual[[#This Row],[Column3]]-1,0) -> 0.1723292 | F4: =IFERROR(Annual[[#This Row],[Column5]]/Annual[[#This Row],[Column4]]-1,0) -> 0.098167523 | G4: =IFERROR(Annual[[#This Row],[Column6]]/Annual[[#This Row],[Column5]]-1,0) -> 0.10662951 | H4: =IFERROR(Annual[[#This Row],[Column7]]/Annual[[#This Row],[Column6]]-1,0) -> 0.21069552 | I4: =IFERROR(Annual[[#This Row],[Column8]]/Annual[[#This Row],[Column7]]-1,0) -> 0.20655864 | J4: =IFERROR(Annual[[#This Row],[Column9]]/Annual[[#This Row],[Column8]]-1,0) -> 0.047033734 | K4: =IFERROR(Annual[[#This Row],[Column10]]/Annual[[#This Row],[Column9]]-1,0) -> 0.060649444 | L4: =IFERROR(Annual[[#This Row],[Column11]]/Annual[[#This Row],[Column10]]-1,0) -> 0.096079514 | M4: =IFERROR(Annual[[#This Row],[Column12]]/Annual[[#This Row],[Column11]]-1,0) -> 0.065925553 | N4: =IFERROR(Annual[[#This Row],[Column13]]/Annual[[#This Row],[Column12]]-1,0) -> 0.069471786 | O4: =IFERROR(Annual[[#This Row],[Column14]]/Annual[[#This Row],[Column13]]-1,0) -> 0.06495897 | P4: =IFERROR(Annual[[#This Row],[Column15]]/Annual[[#This Row],[Column14]]-1,0) -> 0.060996688 | Q4: =IFERROR(Annual[[#This Row],[Column16]]/Annual[[#This Row],[Column15]]-1,0) -> 0.057489989 | U4: =IFERROR(AVERAGE(D4:L4),0) -> 0.11421132 | V4: =IFERROR(MEDIAN(C4:L4),0) -> 0.098167523
B5: EBITDA GROWTH | C5: - | D5: =IFERROR('Profit & Loss'!C14/'Profit & Loss'!B14-1,0) -> 0.022120624 | E5: =IFERROR('Profit & Loss'!D14/'Profit & Loss'!C14-1,0) -> 0.04152171 | F5: =IFERROR('Profit & Loss'!E14/'Profit & Loss'!D14-1,0) -> 0.087541211 | G5: =IFERROR('Profit & Loss'!F14/'Profit & Loss'!E14-1,0) -> 0.20023933 | H5: =IFERROR('Profit & Loss'!G14/'Profit & Loss'!F14-1,0) -> 0.12283151 | I5: =IFERROR('Profit & Loss'!H14/'Profit & Loss'!G14-1,0) -> 0.11972415 | J5: =IFERROR('Profit & Loss'!I14/'Profit & Loss'!H14-1,0) -> 0.087362216 | K5: =IFERROR('Profit & Loss'!J14/'Profit & Loss'!I14-1,0) -> 0.041326332 | ... Q5: =IFERROR('Profit & Loss'!P14/'Profit & Loss'!O14-1,0) -> 0.051632543 | U5: =IFERROR(AVERAGE(D5:L5),0) -> 0.086721363 | V5: =IFERROR(MEDIAN(C5:L5),0) -> 0.087362216
B6: EBT GROWTH | C6: - | D6: =IFERROR('Profit & Loss'!C18/'Profit & Loss'!B18-1,0) -> 0.015989173 | E6: =IFERROR('Profit & Loss'!D18/'Profit & Loss'!C18-1,0) -> 0.038036507 | F6: =IFERROR('Profit & Loss'!E18/'Profit & Loss'!D18-1,0) -> 0.045910365 | G6: =IFERROR('Profit & Loss'!F18/'Profit & Loss'!E18-1,0) -> 0.20997864 | H6: =IFERROR('Profit & Loss'!G18/'Profit & Loss'!F18-1,0) -> 0.13076461 | I6: =IFERROR('Profit & Loss'!H18/'Profit & Loss'!G18-1,0) -> 0.10667552 | J6: =IFERROR('Profit & Loss'!I18/'Profit & Loss'!H18-1,0) -> 0.080007202 | K6: =IFERROR('Profit & Loss'!J18/'Profit & Loss'!I18-1,0) -> 0.045015005 | ... Q6: =IFERROR('Profit & Loss'!P18/'Profit & Loss'!O18-1,0) -> 0.0501572 | U6: =IFERROR(AVERAGE(D6:L6),0) -> 0.081760841 | V6: =IFERROR(MEDIAN(C6:L6),0) -> 0.063470538
B7: NET PROFIT GROWTH | C7: - | D7: =IFERROR('Profit & Loss'!C21/'Profit & Loss'!B21-1,0) -> 0.11677001 | E7: =IFERROR('Profit & Loss'!D21/'Profit & Loss'!C21-1,0) -> -0.038617506 | F7: =IFERROR('Profit & Loss'!E21/'Profit & Loss'!D21-1,0) -> 0.079753407 | G7: =IFERROR('Profit & Loss'!F21/'Profit & Loss'!E21-1,0) -> 0.16731775 | H7: =IFERROR('Profit & Loss'!G21/'Profit & Loss'!F21-1,0) -> 0.14019461 | I7: =IFERROR('Profit & Loss'!H21/'Profit & Loss'!G21-1,0) -> 0.088593877 | J7: =IFERROR('Profit & Loss'!I21/'Profit & Loss'!H21-1,0) -> 0.088767214 | K7: =IFERROR('Profit & Loss'!J21/'Profit & Loss'!I21-1,0) -> 0.019125267 | ... Q7: =IFERROR('Profit & Loss'!P21/'Profit & Loss'!O21-1,0) -> 0.048869965 | U7: =IFERROR(AVERAGE(D7:L7),0) -> 0.084859601 | V7: =IFERROR(MEDIAN(C7:L7),0) -> 0.088767214
B8: DIVIDEND GROWTH | C8: - | D8: =IFERROR('Profit & Loss'!C32/'Profit & Loss'!B32-1,0) -> 0.68963897 | E8: =IFERROR('Profit & Loss'!D32/'Profit & Loss'!C32-1,0) -> -0.02583858 | F8: =IFERROR('Profit & Loss'!E32/'Profit & Loss'!D32-1,0) -> -0.17390646 | G8: =IFERROR('Profit & Loss'!F32/'Profit & Loss'!E32-1,0) -> 0.54369512 | H8: =IFERROR('Profit & Loss'!G32/'Profit & Loss'!F32-1,0) -> 0.14865158 | I8: =IFERROR('Profit & Loss'!H32/'Profit & Loss'!G32-1,0) -> 0.096761529 | J8: =IFERROR('Profit & Loss'!I32/'Profit & Loss'!H32-1,0) -> 0.35349861 | K8: =IFERROR('Profit & Loss'!J32/'Profit & Loss'!I32-1,0) -> -0.064855345 | ... Q8: =IFERROR('Profit & Loss'!P32/'Profit & Loss'!O32-1,0) -> 0.062685596 | U8: =IFERROR(AVERAGE(D8:L8),0) -> 0.18708827 | V8: =IFERROR(MEDIAN(C8:L8),0) -> 0.116149
B11: GROSS MARGIN | C11: =IFERROR('Profit & Loss'!B60,0) -> 0.39315753 | D11: =IFERROR('Profit & Loss'!C60,0) -> 0.38907008 | E11: =IFERROR('Profit & Loss'!D60,0) -> 0.36420925 | F11: =IFERROR('Profit & Loss'!E60,0) -> 0.34567303 | G11: =IFERROR('Profit & Loss'!F60,0) -> 0.34022414 | H11: =IFERROR('Profit & Loss'!G60,0) -> 0.32157743 | I11: =IFERROR('Profit & Loss'!H60,0) -> 0.30380126 | J11: =IFERROR('Profit & Loss'!I60,0) -> 0.31464176 | ... Q11: =IFERROR('Profit & Loss'!P60,0) -> 0.28435351 | U11: =IFERROR(AVERAGE(C11:L11),0) -> 0.33782065 | V11: =IFERROR(MEDIAN(C11:L11),0) -> 0.33090079
B12: EBITDA MARGIN | C12: =IFERROR('Profit & Loss'!B59,0) -> 0.31619064 | D12: =IFERROR('Profit & Loss'!C59,0) -> 0.31384532 | E12: =IFERROR('Profit & Loss'!D59,0) -> 0.27882673 | F12: =IFERROR('Profit & Loss'!E59,0) -> 0.27612869 | G12: =IFERROR('Profit & Loss'!F59,0) -> 0.29948642 | H12: =IFERROR('Profit & Loss'!G59,0) -> 0.27775174 | I12: =IFERROR('Profit & Loss'!H59,0) -> 0.2577623 | J12: =IFERROR('Profit & Loss'!I59,0) -> 0.26769051 | ... Q12: =IFERROR('Profit & Loss'!P59,0) -> 0.24868675 | U12: =IFERROR(AVERAGE(C12:L12),0) -> 0.28041372 | V12: =IFERROR(MEDIAN(C12:L12),0) -> 0.27694022
B13: EBIT MARGIN | C13: =IFERROR((Annual[[#This Row],[Column2]]-'Profit & Loss'!B15)/'Profit & Loss'!B4,0) -> -0.024867122 | D13: =IFERROR((Annual[[#This Row],[Column3]]-'Profit & Loss'!C15)/'Profit & Loss'!C4,0) -> -0.026417288 | E13: =IFERROR((Annual[[#This Row],[Column4]]-'Profit & Loss'!D15)/'Profit & Loss'!D4,0) -> -0.024324161 | F13: =IFERROR((Annual[[#This Row],[Column5]]-'Profit & Loss'!E15)/'Profit & Loss'!E4,0) -> -0.031864392 | G13: =IFERROR((Annual[[#This Row],[Column6]]-'Profit & Loss'!F15)/'Profit & Loss'!F4,0) -> -0.032516522 | H13: =IFERROR((Annual[[#This Row],[Column7]]-'Profit & Loss'!G15)/'Profit & Loss'!G4,0) -> -0.028575891 | I13: =IFERROR((Annual[[#This Row],[Column8]]-'Profit & Loss'!H15)/'Profit & Loss'!H4,0) -> -0.028787125 | J13: =IFERROR((Annual[[#This Row],[Column9]]-'Profit & Loss'!I15)/'Profit & Loss'!I4,0) -> -0.030441856 | K13: =IFERROR((Annual[[#This Row],[Column10]]-'Profit & Loss'!J15)/'Profit & Loss'!J4,0) -> -0.029523284 | L13: =IFERROR((Annual[[#This Row],[Column11]]-'Profit & Loss'!K15)/'Profit & Loss'!K4,0) -> -0.027439127 | M13: =IFERROR((Annual[[#This Row],[Column12]]-'Profit & Loss'!L15)/'Profit & Loss'!L4,0) -> -0.029488723 | N13: =IFERROR((Annual[[#This Row],[Column13]]-'Profit & Loss'!M15)/'Profit & Loss'!M4,0) -> -0.029566238 | O13: =IFERROR((Annual[[#This Row],[Column14]]-'Profit & Loss'!N15)/'Profit & Loss'!N4,0) -> -0.029634297 | P13: =IFERROR((Annual[[#This Row],[Column15]]-'Profit & Loss'!O15)/'Profit & Loss'!O4,0) -> -0.02969453 | Q13: =IFERROR((Annual[[#This Row],[Column12]]-'Profit & Loss'!P15)/'Profit & Loss'!P4,0) -> -0.029748215 | U13: =IFERROR(AVERAGE(C13:L13),0) -> -0.028475677 | V13: =IFERROR(MEDIAN(C13:L13),0) -> -0.028681508
B14: EBT MARGIN | C14: =IFERROR('Profit & Loss'!B62,0) -> 0.29132352 | D14: =IFERROR('Profit & Loss'!C62,0) -> 0.28742804 | E14: =IFERROR('Profit & Loss'!D62,0) -> 0.25450257 | F14: =IFERROR('Profit & Loss'!E62,0) -> 0.24239187 | G14: =IFERROR('Profit & Loss'!F62,0) -> 0.26502906 | H14: =IFERROR('Profit & Loss'!G62,0) -> 0.24753167 | I14: =IFERROR('Profit & Loss'!H62,0) -> 0.22704014 | J14: =IFERROR('Profit & Loss'!I62,0) -> 0.23419015 | ... Q14: =IFERROR('Profit & Loss'!P62,0) -> 0.21584167 | U14: =IFERROR(AVERAGE(C14:L14),0) -> 0.25040486 | V14: =IFERROR(MEDIAN(C14:L14),0) -> 0.24496177
B15: NET PROFIT MARGIN | C15: =IFERROR('Profit & Loss'!B63,0) -> 0.2095818 | D15: =IFERROR('Profit & Loss'!C63,0) -> 0.22729077 | E15: =IFERROR('Profit & Loss'!D63,0) -> 0.1863925 | F15: =IFERROR('Profit & Loss'!E63,0) -> 0.18326706 | G15: =IFERROR('Profit & Loss'!F63,0) -> 0.19331754 | H15: =IFERROR('Profit & Loss'!G63,0) -> 0.18206033 | I15: =IFERROR('Profit & Loss'!H63,0) -> 0.16426036 | J15: =IFERROR('Profit & Loss'!I63,0) -> 0.17080757 | ... Q15: =IFERROR('Profit & Loss'!P63,0) -> 0.15525787 | U15: =IFERROR(AVERAGE(C15:L15),0) -> 0.18460802 | V15: =IFERROR(MEDIAN(C15:L15),0) -> 0.18266369
B20: SALES EXPENSES%SALES | C20: =IFERROR('Profit & Loss'!B12/'Profit & Loss'!B4,0) -> 0.076966883 | D20: =IFERROR('Profit & Loss'!C12/'Profit & Loss'!C4,0) -> 0.075224753 | E20: =IFERROR('Profit & Loss'!D12/'Profit & Loss'!D4,0) -> 0.085382522 | F20: =IFERROR('Profit & Loss'!E12/'Profit & Loss'!E4,0) -> 0.069544338 | G20: =IFERROR('Profit & Loss'!F12/'Profit & Loss'!F4,0) -> 0.040737718 | H20: =IFERROR('Profit & Loss'!G12/'Profit & Loss'!G4,0) -> 0.043825684 | I20: =IFERROR('Profit & Loss'!H12/'Profit & Loss'!H4,0) -> 0.04603896 | J20: =IFERROR('Profit & Loss'!I12/'Profit & Loss'!I4,0) -> 0.046951259 | ... Q20: =IFERROR('Profit & Loss'!P12/'Profit & Loss'!P4,0) -> 0.035666761 | U20: =IFERROR(AVERAGE(C20:L20),0) -> 0.057406923 | V20: =IFERROR(MEDIAN(C20:L20),0) -> 0.046495109
B21: DEPRECIATION%SALES | C21: =IFERROR('Profit & Loss'!B15/'Profit & Loss'!B4,0) -> 0.024867122 | D21: =IFERROR('Profit & Loss'!C15/'Profit & Loss'!C4,0) -> 0.026417288 | E21: =IFERROR('Profit & Loss'!D15/'Profit & Loss'!D4,0) -> 0.024324161 | F21: =IFERROR('Profit & Loss'!E15/'Profit & Loss'!E4,0) -> 0.031864392 | G21: =IFERROR('Profit & Loss'!F15/'Profit & Loss'!F4,0) -> 0.032516522 | H21: =IFERROR('Profit & Loss'!G15/'Profit & Loss'!G4,0) -> 0.028575891 | I21: =IFERROR('Profit & Loss'!H15/'Profit & Loss'!H4,0) -> 0.028787125 | J21: =IFERROR('Profit & Loss'!I15/'Profit & Loss'!I4,0) -> 0.030441856 | ... Q21: =IFERROR('Profit & Loss'!P15/'Profit & Loss'!P4,0) -> 0.029748215 | U21: =IFERROR(AVERAGE(C21:L21),0) -> 0.028475677 | V21: =IFERROR(MEDIAN(C21:L21),0) -> 0.028681508
B22: OPERATING INCOME%SALES | C22: =C13 -> -0.024867122 | D22: =D13 -> -0.026417288 | E22: =E13 -> -0.024324161 | F22: =F13 -> -0.031864392 | G22: =G13 -> -0.032516522 | H22: =H13 -> -0.028575891 | I22: =I13 -> -0.028787125 | J22: =J13 -> -0.030441856 | ... Q22: =Q13 -> -0.029748215 | U22: =IFERROR(AVERAGE(C22:L22),0) -> -0.028475677 | V22: =IFERROR(MEDIAN(C22:L22),0) -> -0.028681508
B25: RETURN ON CAPITAL EMPLOYEE | C25: =IFERROR(('Profit & Loss'!B14-'Profit & Loss'!B15)/SUM('Balance Sheet'!B4:B6),0) -> 0.28922038 | D25: =IFERROR(('Profit & Loss'!C14-'Profit & Loss'!C15)/SUM('Balance Sheet'!C4:C6),0) -> 0.31221601 | E25: =IFERROR(('Profit & Loss'!D14-'Profit & Loss'!D15)/SUM('Balance Sheet'!D4:D6),0) -> 0.32396687 | F25: =IFERROR(('Profit & Loss'!E14-'Profit & Loss'!E15)/SUM('Balance Sheet'!E4:E6),0) -> 0.31643908 | G25: =IFERROR(('Profit & Loss'!F14-'Profit & Loss'!F15)/SUM('Balance Sheet'!F4:F6),0) -> 0.32840737 | H25: =IFERROR(('Profit & Loss'!G14-'Profit & Loss'!G15)/SUM('Balance Sheet'!G4:G6),0) -> 0.37501237 | I25: =IFERROR(('Profit & Loss'!H14-'Profit & Loss'!H15)/SUM('Balance Sheet'!H4:H6),0) -> 0.4014766 | J25: =IFERROR(('Profit & Loss'!I14-'Profit & Loss'!I15)/SUM('Balance Sheet'!I4:I6),0) -> 0.37790101 | ... Q25: =IFERROR(('Profit & Loss'!P14-'Profit & Loss'!P15)/SUM('Balance Sheet'!P4:P6),0) -> 0.42270335 | U25: =IFERROR(AVERAGE(C25:L25),0) -> 0.34861745 | V25: =IFERROR(MEDIAN(C25:L25),0) -> 0.34693231
B26: RETAINED EARNINGS% | C26: =IFERROR('Profit & Loss'!B35,0) -> 0.58952135 | D26: =IFERROR('Profit & Loss'!C35,0) -> 0.40947034 | E26: =IFERROR('Profit & Loss'!D35,0) -> 0.40152498 | F26: =IFERROR('Profit & Loss'!E35,0) -> 0.55363904 | G26: =IFERROR('Profit & Loss'!F35,0) -> 0.4094836 | H26: =IFERROR('Profit & Loss'!G35,0) -> 0.41264337 | I26: =IFERROR('Profit & Loss'!H35,0) -> 0.41640949 | J26: =IFERROR('Profit & Loss'!I35,0) -> 0.2741085 | ... Q26: =IFERROR('Profit & Loss'!P35,0) -> 0.28170351 | U26: =IFERROR(AVERAGE(C26:L26),0) -> 0.41411022 | V26: =IFERROR(MEDIAN(C26:L26),0) -> 0.40947697
B27: RETURN ON EQUITY% | C27: =IFERROR('Profit & Loss'!B21/SUM('Balance Sheet'!B4:B5),0) -> 0.20806877 | D27: =IFERROR('Profit & Loss'!C21/SUM('Balance Sheet'!C4:C5),0) -> 0.24689247 | E27: =IFERROR('Profit & Loss'!D21/SUM('Balance Sheet'!D4:D5),0) -> 0.23726674 | F27: =IFERROR('Profit & Loss'!E21/SUM('Balance Sheet'!E4:E5),0) -> 0.2542246 | G27: =IFERROR('Profit & Loss'!F21/SUM('Balance Sheet'!F4:F5),0) -> 0.25439091 | H27: =IFERROR('Profit & Loss'!G21/SUM('Balance Sheet'!G4:G5),0) -> 0.29390843 | I27: =IFERROR('Profit & Loss'!H21/SUM('Balance Sheet'!H4:H5),0) -> 0.31970507 | J27: =IFERROR('Profit & Loss'!I21/SUM('Balance Sheet'!I4:I5),0) -> 0.29788007 | ... Q27: =IFERROR('Profit & Loss'!P21/SUM('Balance Sheet'!P4:P5),0) -> 0.34355278 | U27: =IFERROR(AVERAGE(C27:L27),0) -> 0.2708942 | V27: =IFERROR(MEDIAN(C27:L27),0) -> 0.266783
B28: SELF SUSTAINED GROWTH RATE | C28: =IFERROR(C26*C27,0) -> 0.12266098 | D28: =IFERROR(D26*D27,0) -> 0.10109514 | E28: =IFERROR(E26*E27,0) -> 0.095268523 | F28: =IFERROR(F26*F27,0) -> 0.14074866 | G28: =IFERROR(G26*G27,0) -> 0.1041689 | H28: =IFERROR(H26*H27,0) -> 0.12127936 | I28: =IFERROR(I26*I27,0) -> 0.13312822 | J28: =IFERROR(J26*J27,0) -> 0.081651459 | ... Q28: =IFERROR(Q26*Q27,0) -> 0.096780027 | U28: =IFERROR(AVERAGE(C28:L28),0) -> 0.11012852 | V28: =IFERROR(MEDIAN(C28:L28),0) -> 0.10616837
B29: INTEREST COVERAGE RATIO | C29: =IFERROR(('Profit & Loss'!B14-'Profit & Loss'!B15)/'Profit & Loss'!B16,0) -> 0 | D29: =IFERROR(('Profit & Loss'!C14-'Profit & Loss'!C15)/'Profit & Loss'!C16,0) -> 0 | E29: =IFERROR(('Profit & Loss'!D14-'Profit & Loss'!D15)/'Profit & Loss'!D16,0) -> 0 | F29: =IFERROR(('Profit & Loss'!E14-'Profit & Loss'!E15)/'Profit & Loss'!E16,0) -> 130.45294 | G29: =IFERROR(('Profit & Loss'!F14-'Profit & Loss'!F15)/'Profit & Loss'!F16,0) -> 137.55385 | H29: =IFERROR(('Profit & Loss'!G14-'Profit & Loss'!G15)/'Profit & Loss'!G16,0) -> 151.55 | I29: =IFERROR(('Profit & Loss'!H14-'Profit & Loss'!H15)/'Profit & Loss'!H16,0) -> 118.33099 | J29: =IFERROR(('Profit & Loss'!I14-'Profit & Loss'!I15)/'Profit & Loss'!I16,0) -> 77.570213 | ... Q29: =IFERROR(('Profit & Loss'!P14-'Profit & Loss'!P15)/'Profit & Loss'!P16,0) -> 70.696876 | U29: =IFERROR(AVERAGE(C29:L29),0) -> 80.400366 | V29: =IFERROR(MEDIAN(C29:L29),0) -> 94.272837
B32: DEBTOR TURNOVER RATIO | C32: =IFERROR('Profit & Loss'!B4/'Balance Sheet'!B16,0) -> 5.557864 | D32: =IFERROR('Profit & Loss'!C4/'Balance Sheet'!C16,0) -> 5.3661543 | E32: =IFERROR('Profit & Loss'!D4/'Balance Sheet'!D16,0) -> 5.5759763 | F32: =IFERROR('Profit & Loss'!E4/'Balance Sheet'!E16,0) -> 4.9110726 | G32: =IFERROR('Profit & Loss'!F4/'Balance Sheet'!F16,0) -> 5.207422 | H32: =IFERROR('Profit & Loss'!G4/'Balance Sheet'!G16,0) -> 5.3591065 | I32: =IFERROR('Profit & Loss'!H4/'Balance Sheet'!H16,0) -> 5.7727738 | J32: =IFERROR('Profit & Loss'!I4/'Balance Sheet'!I16,0) -> 5.0895903 | ... Q32: =IFERROR('Profit & Loss'!P4/'Balance Sheet'!P16,0) -> 0 | U32: =IFERROR(AVERAGE(C32:L32),0) -> 5.3141427 | V32: =IFERROR(MEDIAN(C32:L32),0) -> 5.2950934
B33: CREDITOR TURNOVER RATIO | C33: =IFERROR('Profit & Loss'!B4/'Balance Sheet'!B7,0) -> 4.8343922 | D33: =IFERROR('Profit & Loss'!C4/'Balance Sheet'!C7,0) -> 4.8885346 | E33: =IFERROR('Profit & Loss'!D4/'Balance Sheet'!D7,0) -> 4.3244586 | F33: =IFERROR('Profit & Loss'!E4/'Balance Sheet'!E7,0) -> 4.1806419 | G33: =IFERROR('Profit & Loss'!F4/'Balance Sheet'!F7,0) -> 3.8889878 | H33: =IFERROR('Profit & Loss'!G4/'Balance Sheet'!G7,0) -> 3.3878568 | I33: =IFERROR('Profit & Loss'!H4/'Balance Sheet'!H7,0) -> 3.5893128 | J33: =IFERROR('Profit & Loss'!I4/'Balance Sheet'!I7,0) -> 3.8859527 | ... Q33: =IFERROR('Profit & Loss'!P4/'Balance Sheet'!P7,0) -> 3.3755126 | U33: =IFERROR(AVERAGE(C33:L33),0) -> 4.0124108 | V33: =IFERROR(MEDIAN(C33:L33),0) -> 3.8874703
B34: INVENTORY TURNOVER | C34: =IFERROR('Profit & Loss'!B4/'Balance Sheet'!B17,0) -> 0 | D34: =IFERROR('Profit & Loss'!C4/'Balance Sheet'!C17,0) -> 0 | E34: =IFERROR('Profit & Loss'!D4/'Balance Sheet'!D17,0) -> 0 | F34: =IFERROR('Profit & Loss'!E4/'Balance Sheet'!E17,0) -> 0 | G34: =IFERROR('Profit & Loss'!F4/'Balance Sheet'!F17,0) -> 0 | H34: =IFERROR('Profit & Loss'!G4/'Balance Sheet'!G17,0) -> 0 | I34: =IFERROR('Profit & Loss'!H4/'Balance Sheet'!H17,0) -> 0 | J34: =IFERROR('Profit & Loss'!I4/'Balance Sheet'!I17,0) -> 0 | ... Q34: =IFERROR('Profit & Loss'!P4/'Balance Sheet'!P17,0) -> 0 | U34: =IFERROR(AVERAGE(C34:L34),0) -> 0 | V34: =IFERROR(MEDIAN(C34:L34),0) -> 0
B35: FIXED ASSEST TURNOVER | C35: =IFERROR('Profit & Loss'!B4/'Balance Sheet'!B10,0) -> 4.8299598 | D35: =IFERROR('Profit & Loss'!C4/'Balance Sheet'!C10,0) -> 5.6085573 | E35: =IFERROR('Profit & Loss'!D4/'Balance Sheet'!D10,0) -> 5.2625716 | F35: =IFERROR('Profit & Loss'!E4/'Balance Sheet'!E10,0) -> 3.8165118 | G35: =IFERROR('Profit & Loss'!F4/'Balance Sheet'!F10,0) -> 3.939306 | H35: =IFERROR('Profit & Loss'!G4/'Balance Sheet'!G10,0) -> 4.7147674 | I35: =IFERROR('Profit & Loss'!H4/'Balance Sheet'!H10,0) -> 5.0219675 | J35: =IFERROR('Profit & Loss'!I4/'Balance Sheet'!I10,0) -> 5.5633191 | ... Q35: =IFERROR('Profit & Loss'!P4/'Balance Sheet'!P10,0) -> 5.3061582 | U35: =IFERROR(AVERAGE(C35:L35),0) -> 4.9311524 | V35: =IFERROR(MEDIAN(C35:L35),0) -> 5.1422696
B36: CAPITAL TURNOVER RATIO | C36: =IFERROR('Profit & Loss'!B4/SUM('Balance Sheet'!B4:B5),0) -> 0.99278073 | D36: =IFERROR('Profit & Loss'!C4/SUM('Balance Sheet'!C4:C5),0) -> 1.0862406 | E36: =IFERROR('Profit & Loss'!D4/SUM('Balance Sheet'!D4:D5),0) -> 1.2729414 | F36: =IFERROR('Profit & Loss'!E4/SUM('Balance Sheet'!E4:E5),0) -> 1.3871811 | G36: =IFERROR('Profit & Loss'!F4/SUM('Balance Sheet'!F4:F5),0) -> 1.3159225 | H36: =IFERROR('Profit & Loss'!G4/SUM('Balance Sheet'!G4:G5),0) -> 1.6143464 | I36: =IFERROR('Profit & Loss'!H4/SUM('Balance Sheet'!H4:H5),0) -> 1.9463312 | J36: =IFERROR('Profit & Loss'!I4/SUM('Balance Sheet'!I4:I5),0) -> 1.7439512 | ... Q36: =IFERROR('Profit & Loss'!P4/SUM('Balance Sheet'!P4:P5),0) -> 2.2127882 | U36: =IFERROR(AVERAGE(C36:L36),0) -> 1.4984762 | V36: =IFERROR(MEDIAN(C36:L36),0) -> 1.5007637
B39: DEBTOR DAYS | C39: =IFERROR(365/C32,0) -> 65.672712 | D39: =IFERROR(365/D32,0) -> 68.018916 | E39: =IFERROR(365/E32,0) -> 65.459389 | F39: =IFERROR(365/F32,0) -> 74.321849 | G39: =IFERROR(365/G32,0) -> 70.092265 | H39: =IFERROR(365/H32,0) -> 68.108368 | I39: =IFERROR(365/I32,0) -> 63.227837 | J39: =IFERROR(365/J32,0) -> 71.715006 | ... Q39: =IFERROR(365/Q32,0) -> 0 | U39: =IFERROR(AVERAGE(C39:L39),0) -> 68.837823 | V39: =IFERROR(MEDIAN(C39:L39),0) -> 68.941815
B40: PAYABLE DAYS | C40: =IFERROR(365/C33,0) -> 75.500701 | D40: =IFERROR(365/D33,0) -> 74.664502 | E40: =IFERROR(365/E33,0) -> 84.403629 | F40: =IFERROR(365/F33,0) -> 87.307167 | G40: =IFERROR(365/G33,0) -> 93.854756 | H40: =IFERROR(365/H33,0) -> 107.73773 | I40: =IFERROR(365/I33,0) -> 101.69078 | J40: =IFERROR(365/J33,0) -> 93.92806 | ... Q40: =IFERROR(365/Q33,0) -> 108.13172 | U40: =IFERROR(AVERAGE(C40:L40),0) -> 92.383358 | V40: =IFERROR(MEDIAN(C40:L40),0) -> 93.891408
B41: INVENTORY DAYS | C41: =IFERROR(365/C34,0) -> 0 | D41: =IFERROR(365/D34,0) -> 0 | E41: =IFERROR(365/E34,0) -> 0 | F41: =IFERROR(365/F34,0) -> 0 | G41: =IFERROR(365/G34,0) -> 0 | H41: =IFERROR(365/H34,0) -> 0 | I41: =IFERROR(365/I34,0) -> 0 | J41: =IFERROR(365/J34,0) -> 0 | ... Q41: =IFERROR(365/Q34,0) -> 0 | U41: =IFERROR(AVERAGE(C41:L41),0) -> 0 | V41: =IFERROR(MEDIAN(C41:L41),0) -> 0
B42: CASH CONVERSION CYCLE | C42: =SUM(C39+C41)-C40 -> -9.827989 | D42: =SUM(D39+D41)-D40 -> -6.6455858 | E42: =SUM(E39+E41)-E40 -> -18.944239 | F42: =SUM(F39+F41)-F40 -> -12.985318 | G42: =SUM(G39+G41)-G40 -> -23.762491 | H42: =SUM(H39+H41)-H40 -> -39.62936 | I42: =SUM(I39+I41)-I40 -> -38.462938 | J42: =SUM(J39+J41)-J40 -> -22.213054 | ... Q42: =SUM(Q39+Q41)-Q40 -> -108.13172 | U42: =IFERROR(AVERAGE(C42:L42),0) -> -23.545535 | V42: =IFERROR(MEDIAN(C42:L42),0) -> -22.987772
B45: CFO/SALES | C45: =IFERROR('Cash Flow'!B5/'Profit & Loss'!B4,0) -> 0.16837509 | D45: =IFERROR('Cash Flow'!C5/'Profit & Loss'!C4,0) -> 0.18743087 | E45: =IFERROR('Cash Flow'!D5/'Profit & Loss'!D4,0) -> 0.17951013 | F45: =IFERROR('Cash Flow'!E5/'Profit & Loss'!E4,0) -> 0.18727627 | G45: =IFERROR('Cash Flow'!F5/'Profit & Loss'!F4,0) -> 0.23114898 | H45: =IFERROR('Cash Flow'!G5/'Profit & Loss'!G4,0) -> 0.19635649 | I45: =IFERROR('Cash Flow'!H5/'Profit & Loss'!H4,0) -> 0.15307937 | J45: =IFERROR('Cash Flow'!I5/'Profit & Loss'!I4,0) -> 0.16405284 | ... Q45: =IFERROR('Cash Flow'!P5/'Profit & Loss'!P4,0) -> 0.1921841 | U45: =IFERROR(AVERAGE(C45:L45),0) -> 0.1876463 | V45: =IFERROR(MEDIAN(C45:L45),0) -> 0.18735357
B46: CFO/TOTAL ASSESTS | C46: =IFERROR('Cash Flow'!B5/'Balance Sheet'!B19,0) -> 0.32995679 | D46: =IFERROR('Cash Flow'!C5/'Balance Sheet'!C19,0) -> 0.40103155 | E46: =IFERROR('Cash Flow'!D5/'Balance Sheet'!D19,0) -> 0.43148713 | F46: =IFERROR('Cash Flow'!E5/'Balance Sheet'!E19,0) -> 0.4578576 | G46: =IFERROR('Cash Flow'!F5/'Balance Sheet'!F19,0) -> 0.52772223 | H46: =IFERROR('Cash Flow'!G5/'Balance Sheet'!G19,0) -> 0.59459796 | I46: =IFERROR('Cash Flow'!H5/'Balance Sheet'!H19,0) -> 0.59757427 | J46: =IFERROR('Cash Flow'!I5/'Balance Sheet'!I19,0) -> 0.56048378 | ... Q46: =IFERROR('Cash Flow'!P5/'Balance Sheet'!P19,0) -> 2.5440288 | U46: =IFERROR(AVERAGE(C46:L46),0) -> 0.51342695 | V46: =IFERROR(MEDIAN(C46:L46),0) -> 0.54410301
B47: CFO/TOTAL DEBT | C47: =IFERROR('Cash Flow'!B5/'Balance Sheet'!B6,0) -> 0 | D47: =IFERROR('Cash Flow'!C5/'Balance Sheet'!C6,0) -> 0 | E47: =IFERROR('Cash Flow'!D5/'Balance Sheet'!D6,0) -> 0 | F47: =IFERROR('Cash Flow'!E5/'Balance Sheet'!E6,0) -> 3.6699763 | G47: =IFERROR('Cash Flow'!F5/'Balance Sheet'!F6,0) -> 4.3613146 | H47: =IFERROR('Cash Flow'!G5/'Balance Sheet'!G6,0) -> 4.363354 | I47: =IFERROR('Cash Flow'!H5/'Balance Sheet'!H6,0) -> 2.7071936 | J47: =IFERROR('Cash Flow'!I5/'Balance Sheet'!I6,0) -> 3.015911 | ... Q47: =IFERROR('Cash Flow'!P5/'Balance Sheet'!P6,0) -> 2.9105622 | U47: =IFERROR(AVERAGE(C47:L47),0) -> 2.6160183 | V47: =IFERROR(MEDIAN(C47:L47),0) -> 3.3429436

Sheet FORECASTING
B2: SALES | G2: EBITDA | L2: EPS
B4: YEAR WEIGHT | C4: YEAR | D4: SALES | E4: SALES GROWTH | G4: YEAR WEIGHT | H4: YEAR | I4: EBITDA | J4: EBITDA GROWTH | L4: YEAR WEIGHT | M4: YEAR | N4: EPS | O4: EPS GROWTH
B5: 1 | C5: ='Data Sheet'!$B$16 -> 42825 | D5: {=TRANSPOSE('Data Sheet'!B17:K17)} -> 68484 | G5: 1 | H5: ='Data Sheet'!$B$16 -> 42825 | I5: {=TRANSPOSE('Profit & Loss'!B14:K14)} -> 21654 | L5: 1 | M5: ='Data Sheet'!$B$16 -> 42825 | N5: {=TRANSPOSE('Profit & Loss'!B25:K25)} -> 31.243606
B6: =B5+1 -> 2 | C6: =C5+365 -> 43190 | D6: 70522 | E6: =IFERROR(D6/D5-1,0) -> 0.029758776 | G6: =G5+1 -> 2 | H6: =H5+365 -> 43190 | I6: 22133 | J6: =IFERROR(I6/I5-1,0) -> 0.022120624 | L6: =L5+1 -> 2 | M6: =M5+365 -> 43190 | N6: 36.694748 | O6: =IFERROR(N6/N5-1,0) -> 0.17447227
B7: =B6+1 -> 3 | C7: =C6+365 -> 43555 | D7: 82675 | E7: =IFERROR(D7/D6-1,0) -> 0.1723292 | G7: =G6+1 -> 3 | H7: =H6+365 -> 43555 | I7: 23052 | J7: =IFERROR(I7/I6-1,0) -> 0.04152171 | L7: =L6+1 -> 3 | M7: =M6+365 -> 43555 | N7: 35.272036 | O7: =IFERROR(N7/N6-1,0) -> -0.038771542
B8: =B7+1 -> 4 | C8: =C7+365 -> 43920 | D8: 90791 | E8: =IFERROR(D8/D7-1,0) -> 0.098167523 | G8: =G7+1 -> 4 | H8: =H7+365 -> 43920 | I8: 25070 | J8: =IFERROR(I8/I7-1,0) -> 0.087541211 | L8: =L7+1 -> 4 | M8: =M7+365 -> 43920 | N8: 39.067856 | O8: =IFERROR(N8/N7-1,0) -> 0.10761556
B9: =B8+1 -> 5 | C9: =C8+365 -> 44285 | D9: 100472 | E9: =IFERROR(D9/D8-1,0) -> 0.10662951 | G9: =G8+1 -> 5 | H9: =H8+365 -> 44285 | I9: 30090 | J9: =IFERROR(I9/I8-1,0) -> 0.20023933 | L9: =L8+1 -> 5 | M9: =M8+365 -> 44285 | N9: 45.586406 | O9: =IFERROR(N9/N8-1,0) -> 0.16685199
B10: =B9+1 -> 6 | C10: =C9+365 -> 44650 | D10: 121641 | E10: =IFERROR(D10/D9-1,0) -> 0.21069552 | G10: =G9+1 -> 6 | H10: =H9+365 -> 44650 | I10: 33786 | J10: =IFERROR(I10/I9-1,0) -> 0.12283151 | L10: =L9+1 -> 6 | M10: =M9+365 -> 44650 | N10: 52.644591 | O10: =IFERROR(N10/N9-1,0) -> 0.15483091
B11: =B10+1 -> 7 | C11: =C10+365 -> 45015 | D11: 146767 | E11: =IFERROR(D11/D10-1,0) -> 0.20655864 | G11: =G10+1 -> 7 | H11: =H10+365 -> 45015 | I11: 37831 | J11: =IFERROR(I11/I10-1,0) -> 0.11972415 | L11: =L10+1 -> 7 | M11: =M10+365 -> 45015 | N11: 58.11117 | O11: =IFERROR(N11/N10-1,0) -> 0.10383933
B12: =B11+1 -> 8 | C12: =C11+365 -> 45380 | D12: 153670 | E12: =IFERROR(D12/D11-1,0) -> 0.047033734 | G12: =G11+1 -> 8 | H12: =H11+365 -> 45380 | I12: 41136 | J12: =IFERROR(I12/I11-1,0) -> 0.087362216 | L12: =L11+1 -> 8 | M12: =M11+365 -> 45380 | N12: 63.234479 | O12: =IFERROR(N12/N11-1,0) -> 0.088163932
B13: =B12+1 -> 9 | C13: =C12+365 -> 45745 | D13: 162990 | E13: =IFERROR(D13/D12-1,0) -> 0.060649444 | G13: =G12+1 -> 9 | H13: =H12+365 -> 45745 | I13: 42836 | J13: =IFERROR(I13/I12-1,0) -> 0.041326332 | L13: =L12+1 -> 9 | M13: =M12+365 -> 45745 | N13: 64.406616 | O13: =IFERROR(N13/N12-1,0) -> 0.018536361
B14: =B13+1 -> 10 | C14: =C13+365 -> 46110 | D14: 178650 | E14: =IFERROR(D14/D13-1,0) -> 0.096079514 | G14: =G13+1 -> 10 | H14: =H13+365 -> 46110 | I14: 45313 | J14: =IFERROR(I14/I13-1,0) -> 0.057825194 | L14: =L13+1 -> 10 | M14: =M13+365 -> 46110 | N14: 72.67482 | O14: =IFERROR(N14/N13-1,0) -> 0.12837507
B15: =B14+1 -> 11 | C15: =C14+365 -> 46475 | D15: =FORECAST(B15,$D$5:$D$14,$B$5:$B$14) -> 190427.6 | E15: =IFERROR(D15/D14-1,0) -> 0.065925553 | G15: =G14+1 -> 11 | H15: =H14+365 -> 46475 | I15: {=FORECAST(G15,$I$5:$I$14,$G$5:$G$14)} -> 48631.8 | J15: =IFERROR(I15/I14-1,0) -> 0.073241675 | L15: =L14+1 -> 11 | M15: =M14+365 -> 46475 | N15: =FORECAST(L15,$N$5:$N$14,$L$5:$L$14) -> 75.589111 | O15: =IFERROR(N15/N14-1,0) -> 0.040100424
B16: =B15+1 -> 12 | C16: =C15+365 -> 46840 | D16: =FORECAST(B16,$D$5:$D$14,$B$5:$B$14) -> 203656.95 | E16: =IFERROR(D16/D15-1,0) -> 0.069471786 | G16: =G15+1 -> 12 | H16: =H15+365 -> 46840 | I16: {=FORECAST(G16,$I$5:$I$14,$G$5:$G$14)} -> 51603.018 | J16: =IFERROR(I16/I15-1,0) -> 0.0610962 | L16: =L15+1 -> 12 | M16: =M15+365 -> 46840 | N16: =FORECAST(L16,$N$5:$N$14,$L$5:$L$14) -> 80.261016 | O16: =IFERROR(N16/N15-1,0) -> 0.061806589
B17: =B16+1 -> 13 | C17: =C16+365 -> 47205 | D17: =FORECAST(B17,$D$5:$D$14,$B$5:$B$14) -> 216886.29 | E17: =IFERROR(D17/D16-1,0) -> 0.06495897 | G17: =G16+1 -> 13 | H17: =H16+365 -> 47205 | I17: {=FORECAST(G17,$I$5:$I$14,$G$5:$G$14)} -> 54574.236 | J17: =IFERROR(I17/I16-1,0) -> 0.05757838 | L17: =L16+1 -> 13 | M17: =M16+365 -> 47205 | N17: =FORECAST(L17,$N$5:$N$14,$L$5:$L$14) -> 84.932921 | O17: =IFERROR(N17/N16-1,0) -> 0.058208896
B18: =B17+1 -> 14 | C18: =C17+365 -> 47570 | D18: =FORECAST(B18,$D$5:$D$14,$B$5:$B$14) -> 230115.64 | E18: =IFERROR(D18/D17-1,0) -> 0.060996688 | G18: =G17+1 -> 14 | H18: =H17+365 -> 47570 | I18: {=FORECAST(G18,$I$5:$I$14,$G$5:$G$14)} -> 57545.455 | J18: =IFERROR(I18/I17-1,0) -> 0.054443605 | L18: =L17+1 -> 14 | M18: =M17+365 -> 47570 | N18: =FORECAST(L18,$N$5:$N$14,$L$5:$L$14) -> 89.604826 | O18: =IFERROR(N18/N17-1,0) -> 0.055006999
B19: =B18+1 -> 15 | C19: =C18+365 -> 47935 | D19: =FORECAST(B19,$D$5:$D$14,$B$5:$B$14) -> 243344.98 | E19: =IFERROR(D19/D18-1,0) -> 0.057489989 | G19: =G18+1 -> 15 | H19: =H18+365 -> 47935 | I19: {=FORECAST(G19,$I$5:$I$14,$G$5:$G$14)} -> 60516.673 | J19: =IFERROR(I19/I18-1,0) -> 0.051632543 | L19: =L18+1 -> 15 | M19: =M18+365 -> 47935 | N19: =FORECAST(L19,$N$5:$N$14,$L$5:$L$14) -> 94.276732 | O19: =IFERROR(N19/N18-1,0) -> 0.05213899
B23: EXPENSES | G23: 0THER INCOME | L23: SG&A
B25: YEAR WEIGHT | C25: YEAR | D25: EXPENSES | E25: EXPENSES GROWTH | G25: YEAR WEIGHT | H25: YEAR | I25: OTHER INCOME | J25: OTHER INCOME GROWTH | L25: YEAR WEIGHT | M25: YEAR | N25: SG&A | O25: SG&A GROWTH
B26: 1 | C26: ='Data Sheet'!$B$16 -> 42825 | D26: {=TRANSPOSE('Profit & Loss'!B6:K6)} -> 44609 | G26: 1 | H26: ='Data Sheet'!$B$16 -> 42825 | I26: {=TRANSPOSE('Profit & Loss'!B9:K9)} -> 3050 | L26: 1 | M26: ='Data Sheet'!$B$16 -> 42825 | N26: {=TRANSPOSE('Profit & Loss'!B12:K12)} -> 5271
B27: =B26+1 -> 2 | C27: =C26+365 -> 43190 | D27: 46395 | E27: =IFERROR(D27/D26-1,0) -> 0.040036764 | G27: =G26+1 -> 2 | H27: =H26+365 -> 43190 | I27: 3311 | J27: =IFERROR(I27/I26-1,0) -> 0.08557377 | L27: =L26+1 -> 2 | M27: =M26+365 -> 43190 | N27: 5305 | O27: =IFERROR(N27/N26-1,0) -> 0.0064503889
B28: =B27+1 -> 3 | C28: =C27+365 -> 43555 | D28: 55446 | E28: =IFERROR(D28/D27-1,0) -> 0.19508568 | G28: =G27+1 -> 3 | H28: =H27+365 -> 43555 | I28: 2882 | J28: =IFERROR(I28/I27-1,0) -> -0.12956811 | L28: =L27+1 -> 3 | M28: =M27+365 -> 43555 | N28: 7059 | O28: =IFERROR(N28/N27-1,0) -> 0.33063148
B29: =B28+1 -> 4 | C29: =C28+365 -> 43920 | D29: 62210 | E29: =IFERROR(D29/D28-1,0) -> 0.12199257 | G29: =G28+1 -> 4 | H29: =H28+365 -> 43920 | I29: 2803 | J29: =IFERROR(I29/I28-1,0) -> -0.02741152 | L29: =L28+1 -> 4 | M29: =M28+365 -> 43920 | N29: 6314 | O29: =IFERROR(N29/N28-1,0) -> -0.10553903
B30: =B29+1 -> 5 | C30: =C29+365 -> 44285 | D30: 68490 | E30: =IFERROR(D30/D29-1,0) -> 0.1009484 | G30: =G29+1 -> 5 | H30: =H29+365 -> 44285 | I30: 2201 | J30: =IFERROR(I30/I29-1,0) -> -0.21476989 | L30: =L29+1 -> 5 | M30: =M29+365 -> 44285 | N30: 4093 | O30: =IFERROR(N30/N29-1,0) -> -0.351758
B31: =B30+1 -> 6 | C31: =C30+365 -> 44650 | D31: 84819 | E31: =IFERROR(D31/D30-1,0) -> 0.23841437 | G31: =G30+1 -> 6 | H31: =H30+365 -> 44650 | I31: 2295 | J31: =IFERROR(I31/I30-1,0) -> 0.04270786 | L31: =L30+1 -> 6 | M31: =M30+365 -> 44650 | N31: 5331 | O31: =IFERROR(N31/N30-1,0) -> 0.30246763
B32: =B31+1 -> 7 | C32: =C31+365 -> 45015 | D32: 104880 | E32: =IFERROR(D32/D31-1,0) -> 0.2365154 | G32: =G31+1 -> 7 | H32: =H31+365 -> 45015 | I32: 2701 | J32: =IFERROR(I32/I31-1,0) -> 0.17690632 | L32: =L31+1 -> 7 | M32: =M31+365 -> 45015 | N32: 6757 | O32: =IFERROR(N32/N31-1,0) -> 0.26749203
B33: =B32+1 -> 8 | C33: =C32+365 -> 45380 | D33: 110030 | E33: =IFERROR(D33/D32-1,0) -> 0.049103738 | G33: =G32+1 -> 8 | H33: =H32+365 -> 45380 | I33: 4711 | J33: =IFERROR(I33/I32-1,0) -> 0.74416883 | L33: =L32+1 -> 8 | M33: =M32+365 -> 45380 | N33: 7215 | O33: =IFERROR(N33/N32-1,0) -> 0.06778156
B34: =B33+1 -> 9 | C34: =C33+365 -> 45745 | D34: 116585 | E34: =IFERROR(D34/D33-1,0) -> 0.059574661 | G34: =G33+1 -> 9 | H34: =H33+365 -> 45745 | I34: 3600 | J34: =IFERROR(I34/I33-1,0) -> -0.23583103 | L34: =L33+1 -> 9 | M34: =M33+365 -> 45745 | N34: 7169 | O34: =IFERROR(N34/N33-1,0) -> -0.0063756064
B35: =B34+1 -> 10 | C35: =C34+365 -> 46110 | D35: 128257 | E35: =IFERROR(D35/D34-1,0) -> 0.1001158 | G35: =G34+1 -> 10 | H35: =H34+365 -> 46110 | I35: 3033 | J35: =IFERROR(I35/I34-1,0) -> -0.1575 | L35: =L34+1 -> 10 | M35: =M34+365 -> 46110 | N35: 8113 | O35: =IFERROR(N35/N34-1,0) -> 0.13167806
B36: =B35+1 -> 11 | C36: =C35+365 -> 46475 | D36: =FORECAST(B36,$D$26:$D$35,$B$26:$B$35) -> 137552.8 | E36: =IFERROR(D36/D35-1,0) -> 0.072477915 | G36: =G35+1 -> 11 | H36: =H35+365 -> 46475 | I36: =FORECAST(G36,$I$26:$I$35,$G$26:$G$35) -> 3418.8 | J36: =IFERROR(I36/I35-1,0) -> 0.12720079 | L36: =L35+1 -> 11 | M36: =M35+365 -> 46475 | N36: =FORECAST(L36,$N$26:$N$35,$L$26:$L$35) -> 7661.8 | O36: =IFERROR(N36/N35-1,0) -> -0.055614446
B37: =B36+1 -> 12 | C37: =C36+365 -> 46840 | D37: =FORECAST(B37,$D$26:$D$35,$B$26:$B$35) -> 147622.02 | E37: =IFERROR(D37/D36-1,0) -> 0.073202568 | G37: =G36+1 -> 12 | H37: =H36+365 -> 46840 | I37: =FORECAST(G37,$I$26:$I$35,$G$26:$G$35) -> 3484.2727 | J37: =IFERROR(I37/I36-1,0) -> 0.019150792 | L37: =L36+1 -> 12 | M37: =M36+365 -> 46840 | N37: =FORECAST(L37,$N$26:$N$35,$L$26:$L$35) -> 7916.1818 | O37: =IFERROR(N37/N36-1,0) -> 0.033201313
B38: =B37+1 -> 13 | C38: =C37+365 -> 47205 | D38: =FORECAST(B38,$D$26:$D$35,$B$26:$B$35) -> 157691.24 | E38: =IFERROR(D38/D37-1,0) -> 0.06820946 | G38: =G37+1 -> 13 | H38: =H37+365 -> 47205 | I38: =FORECAST(G38,$I$26:$I$35,$G$26:$G$35) -> 3549.7455 | J38: =IFERROR(I38/I37-1,0) -> 0.018790931 | L38: =L37+1 -> 13 | M38: =M37+365 -> 47205 | N38: =FORECAST(L38,$N$26:$N$35,$L$26:$L$35) -> 8170.5636 | O38: =IFERROR(N38/N37-1,0) -> 0.032134408
B39: =B38+1 -> 14 | C39: =C38+365 -> 47570 | D39: =FORECAST(B39,$D$26:$D$35,$B$26:$B$35) -> 167760.45 | E39: =IFERROR(D39/D38-1,0) -> 0.063854013 | G39: =G38+1 -> 14 | H39: =H38+365 -> 47570 | I39: =FORECAST(G39,$I$26:$I$35,$G$26:$G$35) -> 3615.2182 | J39: =IFERROR(I39/I38-1,0) -> 0.018444344 | L39: =L38+1 -> 14 | M39: =M38+365 -> 47570 | N39: =FORECAST(L39,$N$26:$N$35,$L$26:$L$35) -> 8424.9455 | O39: =IFERROR(N39/N38-1,0) -> 0.031133938
B40: =B39+1 -> 15 | C40: =C39+365 -> 47935 | D40: =FORECAST(B40,$D$26:$D$35,$B$26:$B$35) -> 177829.67 | E40: =IFERROR(D40/D39-1,0) -> 0.060021405 | G40: =G39+1 -> 15 | H40: =H39+365 -> 47935 | I40: =FORECAST(G40,$I$26:$I$35,$G$26:$G$35) -> 3680.6909 | J40: =IFERROR(I40/I39-1,0) -> 0.018110311 | L40: =L39+1 -> 15 | M40: =M39+365 -> 47935 | N40: =FORECAST(L40,$N$26:$N$35,$L$26:$L$35) -> 8679.3273 | O40: =IFERROR(N40/N39-1,0) -> 0.030193883
B43: INTEREST | G43: TAX | L43: DEPR.
B45: YEAR WEIGHT | C45: YEAR | D45: INTEREST | E45: INTEREST GROWTH | G45: YEAR WEIGHT | H45: YEAR | I45: TAX | J45: TAX GROWTH | L45: YEAR WEIGHT | M45: YEAR | N45: DEPR. | O45: DEPR. GROWTH
B46: 1 | C46: ='Data Sheet'!$B$16 -> 42825 | D46: {=TRANSPOSE('Profit & Loss'!B16:K16)} -> 0 | G46: 1 | H46: ='Data Sheet'!$B$16 -> 42825 | I46: {=TRANSPOSE('Profit & Loss'!B19:K19)} -> 5598 | L46: 1 | M46: ='Data Sheet'!$B$16 -> 42825 | N46: {=TRANSPOSE('Profit & Loss'!B15:K15)} -> 1703
B47: =B46+1 -> 2 | C47: =C46+365 -> 43190 | D47: 0 | E47: =IFERROR(D47/D46-1,0) -> 0 | G47: =G46+1 -> 2 | H47: =H46+365 -> 43190 | I47: 4241 | J47: =IFERROR(I47/I46-1,0) -> -0.242408 | L47: =L46+1 -> 2 | M47: =M46+365 -> 43190 | N47: 1863 | O47: =IFERROR(N47/N46-1,0) -> 0.09395185
B48: =B47+1 -> 3 | C48: =C47+365 -> 43555 | D48: 0 | E48: =IFERROR(D48/D47-1,0) -> 0 | G48: =G47+1 -> 3 | H48: =H47+365 -> 43555 | I48: 5631 | J48: =IFERROR(I48/I47-1,0) -> 0.32775289 | L48: =L47+1 -> 3 | M48: =M47+365 -> 43555 | N48: 2011 | O48: =IFERROR(N48/N47-1,0) -> 0.079441761
B49: =B48+1 -> 4 | C49: =C48+365 -> 43920 | D49: 170 | E49: =IFERROR(D49/D48-1,0) -> 0 | G49: =G48+1 -> 4 | H49: =H48+365 -> 43920 | I49: 5368 | J49: =IFERROR(I49/I48-1,0) -> -0.046705736 | L49: =L48+1 -> 4 | M49: =M48+365 -> 43920 | N49: 2893 | O49: =IFERROR(N49/N48-1,0) -> 0.43858777
B50: =B49+1 -> 5 | C50: =C49+365 -> 44285 | D50: 195 | E50: =IFERROR(D50/D49-1,0) -> 0.14705882 | G50: =G49+1 -> 5 | H50: =H49+365 -> 44285 | I50: 7205 | J50: =IFERROR(I50/I49-1,0) -> 0.34221311 | L50: =L49+1 -> 5 | M50: =M49+365 -> 44285 | N50: 3267 | O50: =IFERROR(N50/N49-1,0) -> 0.12927757
B51: =B50+1 -> 6 | C51: =C50+365 -> 44650 | D51: 200 | E51: =IFERROR(D51/D50-1,0) -> 0.025641026 | G51: =G50+1 -> 6 | H51: =H50+365 -> 44650 | I51: 7964 | J51: =IFERROR(I51/I50-1,0) -> 0.10534351 | L51: =L50+1 -> 6 | M51: =M50+365 -> 44650 | N51: 3476 | O51: =IFERROR(N51/N50-1,0) -> 0.063973064
B52: =B51+1 -> 7 | C52: =C51+365 -> 45015 | D52: 284 | E52: =IFERROR(D52/D51-1,0) -> 0.42 | G52: =G51+1 -> 7 | H52: =H51+365 -> 45015 | I52: 9214 | J52: =IFERROR(I52/I51-1,0) -> 0.1569563 | L52: =L51+1 -> 7 | M52: =M51+365 -> 45015 | N52: 4225 | O52: =IFERROR(N52/N51-1,0) -> 0.21547756
B53: =B52+1 -> 8 | C53: =C52+365 -> 45380 | D53: 470 | E53: =IFERROR(D53/D52-1,0) -> 0.65492958 | G53: =G52+1 -> 8 | H53: =H52+365 -> 45380 | I53: 9740 | J53: =IFERROR(I53/I52-1,0) -> 0.057087041 | L53: =L52+1 -> 8 | M53: =M52+365 -> 45380 | N53: 4678 | O53: =IFERROR(N53/N52-1,0) -> 0.10721893
B54: =B53+1 -> 9 | C54: =C53+365 -> 45745 | D54: 416 | E54: =IFERROR(D54/D53-1,0) -> -0.11489362 | G54: =G53+1 -> 9 | H54: =H53+365 -> 45745 | I54: 10858 | J54: =IFERROR(I54/I53-1,0) -> 0.11478439 | L54: =L53+1 -> 9 | M54: =M53+365 -> 45745 | N54: 4812 | O54: =IFERROR(N54/N53-1,0) -> 0.02864472
B55: =B54+1 -> 10 | C55: =C54+365 -> 46110 | D55: 416 | E55: =IFERROR(D55/D54-1,0) -> 0 | G55: =G54+1 -> 10 | H55: =H54+365 -> 46110 | I55: 10521 | J55: =IFERROR(I55/I54-1,0) -> -0.031037023 | L55: =L54+1 -> 10 | M55: =M54+365 -> 46110 | N55: 4902 | O55: =IFERROR(N55/N54-1,0) -> 0.018703242
B56: =B55+1 -> 11 | C56: =C55+365 -> 46475 | D56: {=FORECAST(B56,$D$46:$D$55,$B$46:$B$55)} -> 526.86667 | E56: =IFERROR(D56/D55-1,0) -> 0.26650641 | G56: =G55+1 -> 11 | H56: =H55+365 -> 46475 | I56: {=FORECAST(G56,$I$46:$I$55,$G$46:$G$55)} -> 11749.6 | J56: =IFERROR(I56/I55-1,0) -> 0.11677597 | L56: =L55+1 -> 11 | M56: =M55+365 -> 46475 | N56: =FORECAST(L56,$N$46:$N$55,$L$46:$L$55) -> 5615.4667 | O56: =IFERROR(N56/N55-1,0) -> 0.14554604
B57: =B56+1 -> 12 | C57: =C56+365 -> 46840 | D57: {=FORECAST(B57,$D$46:$D$55,$B$46:$B$55)} -> 583.55152 | E57: =IFERROR(D57/D56-1,0) -> 0.1075886 | G57: =G56+1 -> 12 | H57: =H56+365 -> 46840 | I57: {=FORECAST(G57,$I$46:$I$55,$G$46:$G$55)} -> 12497.891 | J57: =IFERROR(I57/I56-1,0) -> 0.063686501 | L57: =L56+1 -> 12 | M57: =M56+365 -> 46840 | N57: =FORECAST(L57,$N$46:$N$55,$L$46:$L$55) -> 6021.3697 | O57: =IFERROR(N57/N56-1,0) -> 0.072283045
B58: =B57+1 -> 13 | C58: =C57+365 -> 47205 | D58: {=FORECAST(B58,$D$46:$D$55,$B$46:$B$55)} -> 640.23636 | E58: =IFERROR(D58/D57-1,0) -> 0.097137694 | G58: =G57+1 -> 13 | H58: =H57+365 -> 47205 | I58: {=FORECAST(G58,$I$46:$I$55,$G$46:$G$55)} -> 13246.182 | J58: =IFERROR(I58/I57-1,0) -> 0.059873375 | L58: =L57+1 -> 13 | M58: =M57+365 -> 47205 | N58: =FORECAST(L58,$N$46:$N$55,$L$46:$L$55) -> 6427.2727 | O58: =IFERROR(N58/N57-1,0) -> 0.067410415
B59: =B58+1 -> 14 | C59: =C58+365 -> 47570 | D59: {=FORECAST(B59,$D$46:$D$55,$B$46:$B$55)} -> 696.92121 | E59: =IFERROR(D59/D58-1,0) -> 0.088537377 | G59: =G58+1 -> 14 | H59: =H58+365 -> 47570 | I59: {=FORECAST(G59,$I$46:$I$55,$G$46:$G$55)} -> 13994.473 | J59: =IFERROR(I59/I58-1,0) -> 0.056491064 | L59: =L58+1 -> 14 | M59: =M58+365 -> 47570 | N59: =FORECAST(L59,$N$46:$N$55,$L$46:$L$55) -> 6833.1758 | O59: =IFERROR(N59/N58-1,0) -> 0.06315323
B60: =B59+1 -> 15 | C60: =C59+365 -> 47935 | D60: {=FORECAST(B60,$D$46:$D$55,$B$46:$B$55)} -> 753.60606 | E60: =IFERROR(D60/D59-1,0) -> 0.081336093 | G60: =G59+1 -> 15 | H60: =H59+365 -> 47935 | I60: {=FORECAST(G60,$I$46:$I$55,$G$46:$G$55)} -> 14742.764 | J60: =IFERROR(I60/I59-1,0) -> 0.053470461 | L60: =L59+1 -> 15 | M60: =M59+365 -> 47935 | N60: =FORECAST(L60,$N$46:$N$55,$L$46:$L$55) -> 7239.0788 | O60: =IFERROR(N60/N59-1,0) -> 0.059401813
B63: PRICE | G63: DIVIDEND AMOUNT | L63: EQUITY SHARE CAPITAL
B65: YEAR WEIGHT | C65: YEAR | D65: PRICE | E65: PRICE GROWTH | G65: YEAR WEIGHT | H65: YEAR | I65: DIVI.AMOUNT | J65: DIVI.AMOUNT GROWTH | L65: YEAR WEIGHT | M65: YEAR | N65: E.S.C | O65: E.S.C GROWTH
B66: 1 | C66: ='Data Sheet'!$B$16 -> 42825 | D66: {=TRANSPOSE('Profit & Loss'!B29:K29)} -> 511.13 | G66: 1 | H66: ='Data Sheet'!$B$16 -> 42825 | I66: {=TRANSPOSE('Data Sheet'!B31:K31)} -> 5891.6 | L66: 1 | M66: ='Data Sheet'!$B$16 -> 42825 | N66: {=TRANSPOSE('Balance Sheet'!B4:K4)} -> 1144
B67: =B66+1 -> 2 | C67: =C66+365 -> 43190 | D67: 565.9 | E67: =IFERROR(D67/D66-1,0) -> 0.10715474 | G67: =G66+1 -> 2 | H67: =H66+365 -> 43190 | I67: 9465.6 | J67: =IFERROR(I67/I66-1,0) -> 0.60662638 | L67: =L66+1 -> 2 | M67: =M66+365 -> 43190 | N67: 1088 | O67: =IFERROR(N67/N66-1,0) -> -0.048951049
B68: =B67+1 -> 3 | C68: =C67+365 -> 43555 | D68: 743.85 | E68: =IFERROR(D68/D67-1,0) -> 0.31445485 | G68: =G67+1 -> 3 | H68: =H67+365 -> 43555 | I68: 9222.5 | J68: =IFERROR(I68/I67-1,0) -> -0.025682471 | L68: =L67+1 -> 3 | M68: =M67+365 -> 43555 | N68: 2170 | O68: =IFERROR(N68/N67-1,0) -> 0.99448529
B69: =B68+1 -> 4 | C69: =C68+365 -> 43920 | D69: 641.5 | E69: =IFERROR(D69/D68-1,0) -> -0.13759495 | G69: =G68+1 -> 4 | H69: =H68+365 -> 43920 | I69: 7427 | J69: =IFERROR(I69/I68-1,0) -> -0.19468691 | L69: =L68+1 -> 4 | M69: =M68+365 -> 43920 | N69: 2122 | O69: =IFERROR(N69/N68-1,0) -> -0.022119816
B70: =B69+1 -> 5 | C70: =C69+365 -> 44285 | D70: 1368.05 | E70: =IFERROR(D70/D69-1,0) -> 1.1325799 | G70: =G69+1 -> 5 | H70: =H69+365 -> 44285 | I70: 11469.6 | J70: =IFERROR(I70/I69-1,0) -> 0.5443113 | L70: =L69+1 -> 5 | M70: =M69+365 -> 44285 | N70: 2124 | O70: =IFERROR(N70/N69-1,0) -> 0.00094250707
B71: =B70+1 -> 6 | C71: =C70+365 -> 44650 | D71: 1906.85 | E71: =IFERROR(D71/D70-1,0) -> 0.39384525 | G71: =G70+1 -> 6 | H71: =H70+365 -> 44650 | I71: 13007.6 | J71: =IFERROR(I71/I70-1,0) -> 0.1340936 | L71: =L70+1 -> 6 | M71: =M70+365 -> 44650 | N71: 2098 | O71: =IFERROR(N71/N70-1,0) -> -0.012241055
B72: =B71+1 -> 7 | C72: =C71+365 -> 45015 | D72: 1427.95 | E72: =IFERROR(D72/D71-1,0) -> -0.25114718 | G72: =G71+1 -> 7 | H72: =H71+365 -> 45015 | I72: 14069.2 | J72: =IFERROR(I72/I71-1,0) -> 0.081613826 | L72: =L71+1 -> 7 | M72: =M71+365 -> 45015 | N72: 2069 | O72: =IFERROR(N72/N71-1,0) -> -0.013822688
B73: =B72+1 -> 8 | C73: =C72+365 -> 45380 | D73: 1498.05 | E73: =IFERROR(D73/D72-1,0) -> 0.049091355 | G73: =G72+1 -> 8 | H73: =H72+365 -> 45380 | I73: 19053.2 | J73: =IFERROR(I73/I72-1,0) -> 0.354249 | L73: =L72+1 -> 8 | M73: =M72+365 -> 45380 | N73: 2071 | O73: =IFERROR(N73/N72-1,0) -> 0.00096665056
B74: =B73+1 -> 9 | C74: =C73+365 -> 45745 | D74: 1570.65 | E74: =IFERROR(D74/D73-1,0) -> 0.048463002 | G74: =G73+1 -> 9 | H74: =H73+365 -> 45745 | I74: 17827.8 | J74: =IFERROR(I74/I73-1,0) -> -0.064314656 | L74: =L73+1 -> 9 | M74: =M73+365 -> 45745 | N74: 2073 | O74: =IFERROR(N74/N73-1,0) -> 0.00096571704
B75: =B74+1 -> 10 | C75: =C74+365 -> 46110 | D75: 1250.6 | E75: =IFERROR(D75/D74-1,0) -> -0.20376914 | G75: =G74+1 -> 10 | H75: =H74+365 -> 46110 | I75: 19430.4 | J75: =IFERROR(I75/I74-1,0) -> 0.089893313 | L75: =L74+1 -> 10 | M75: =M74+365 -> 46110 | N75: 2024 | O75: =IFERROR(N75/N74-1,0) -> -0.023637241
B76: =B75+1 -> 11 | C76: =C75+365 -> 46475 | D76: {=FORECAST(B76,$D$66:$D$75,$B$66:$B$75)} -> 1827.0407 | E76: =IFERROR(D76/D75-1,0) -> 0.46093129 | G76: =G75+1 -> 11 | H76: =H75+365 -> 46475 | I76: {=FORECAST(G76,$I$66:$I$75,$G$66:$G$75)} -> 21053.207 | J76: =IFERROR(I76/I75-1,0) -> 0.083518953 | L76: =L75+1 -> 11 | M76: =M75+365 -> 46475 | N76: {=FORECAST(L76,$N$66:$N$75,$L$66:$L$75)} -> 2369.4667 | O76: =IFERROR(N76/N75-1,0) -> 0.17068511
B77: =B76+1 -> 12 | C77: =C76+365 -> 46840 | D77: {=FORECAST(B77,$D$66:$D$75,$B$66:$B$75)} -> 1950.4202 | E77: =IFERROR(D77/D76-1,0) -> 0.067529737 | G77: =G76+1 -> 12 | H77: =H76+365 -> 46840 | I77: {=FORECAST(G77,$I$66:$I$75,$G$66:$G$75)} -> 22574.435 | J77: =IFERROR(I77/I76-1,0) -> 0.072256379 | L77: =L76+1 -> 12 | M77: =M76+365 -> 46840 | N77: {=FORECAST(L77,$N$66:$N$75,$L$66:$L$75)} -> 2455.1333 | O77: =IFERROR(N77/N76-1,0) -> 0.036154409
B78: =B77+1 -> 13 | C78: =C77+365 -> 47205 | D78: {=FORECAST(B78,$D$66:$D$75,$B$66:$B$75)} -> 2073.7998 | E78: =IFERROR(D78/D77-1,0) -> 0.063257945 | G78: =G77+1 -> 13 | H78: =H77+365 -> 47205 | I78: {=FORECAST(G78,$I$66:$I$75,$G$66:$G$75)} -> 24095.664 | J78: =IFERROR(I78/I77-1,0) -> 0.067387223 | L78: =L77+1 -> 13 | M78: =M77+365 -> 47205 | N78: {=FORECAST(L78,$N$66:$N$75,$L$66:$L$75)} -> 2540.8 | O78: =IFERROR(N78/N77-1,0) -> 0.034892878
B79: =B78+1 -> 14 | C79: =C78+365 -> 47570 | D79: {=FORECAST(B79,$D$66:$D$75,$B$66:$B$75)} -> 2197.1794 | E79: =IFERROR(D79/D78-1,0) -> 0.059494448 | G79: =G78+1 -> 14 | H79: =H78+365 -> 47570 | I79: {=FORECAST(G79,$I$66:$I$75,$G$66:$G$75)} -> 25616.892 | J79: =IFERROR(I79/I78-1,0) -> 0.063132874 | L79: =L78+1 -> 14 | M79: =M78+365 -> 47570 | N79: {=FORECAST(L79,$N$66:$N$75,$L$66:$L$75)} -> 2626.4667 | O79: =IFERROR(N79/N78-1,0) -> 0.033716415
B80: =B79+1 -> 15 | C80: =C79+365 -> 47935 | D80: {=FORECAST(B80,$D$66:$D$75,$B$66:$B$75)} -> 2320.559 | E80: =IFERROR(D80/D79-1,0) -> 0.05615362 | G80: =G79+1 -> 15 | H80: =H79+365 -> 47935 | I80: {=FORECAST(G80,$I$66:$I$75,$G$66:$G$75)} -> 27138.121 | J80: =IFERROR(I80/I79-1,0) -> 0.059383803 | L80: =L79+1 -> 15 | M80: =M79+365 -> 47935 | N80: {=FORECAST(L80,$N$66:$N$75,$L$66:$L$75)} -> 2712.1333 | O80: =IFERROR(N80/N79-1,0) -> 0.032616697
B83: RESERVES | G83: BORROWINGS | L83: OTHER LIABILITIES
B85: YEAR WEIGHT | C85: YEAR | D85: RESERVES | E85: RESERVES GROWTH | G85: YEAR WEIGHT | H85: YEAR | I85: BORROWINGS | J85: BORROWINGS GROWTH | L85: YEAR WEIGHT | M85: YEAR | N85: OTHER LIABILITIES | O85: OTHER LIABILITIES GROWTH
B86: 1 | C86: ='Data Sheet'!$B$16 -> 42825 | D86: {=TRANSPOSE('Balance Sheet'!B5:K5)} -> 67838 | G86: 1 | H86: ='Data Sheet'!$B$16 -> 42825 | I86: {=TRANSPOSE('Balance Sheet'!B6:K6)} -> 0 | L86: 1 | M86: ='Data Sheet'!$B$16 -> 42825 | N86: {=TRANSPOSE('Balance Sheet'!B7:K7)} -> 14166
B87: =B86+1 -> 2 | C87: =C86+365 -> 43190 | D87: 63835 | E87: =IFERROR(D87/D86-1,0) -> -0.059008225 | G87: =G86+1 -> 2 | H87: =H86+365 -> 43190 | I87: 0 | J87: =IFERROR(I87/I86-1,0) -> 0 | L87: =L86+1 -> 2 | M87: =M86+365 -> 43190 | N87: 14426 | O87: =IFERROR(N87/N86-1,0) -> 0.018353805
B88: =B87+1 -> 3 | C88: =C87+365 -> 43555 | D88: 62778 | E88: =IFERROR(D88/D87-1,0) -> -0.016558314 | G88: =G87+1 -> 3 | H88: =H87+365 -> 43555 | I88: 0 | J88: =IFERROR(I88/I87-1,0) -> 0 | L88: =L87+1 -> 3 | M88: =M87+365 -> 43555 | N88: 19118 | O88: =IFERROR(N88/N87-1,0) -> 0.32524608
B89: =B88+1 -> 4 | C89: =C88+365 -> 43920 | D89: 63328 | E89: =IFERROR(D89/D88-1,0) -> 0.0087610309 | G89: =G88+1 -> 4 | H89: =H88+365 -> 43920 | I89: 4633 | J89: =IFERROR(I89/I88-1,0) -> 0 | L89: =L88+1 -> 4 | M89: =M88+365 -> 43920 | N89: 21717 | O89: =IFERROR(N89/N88-1,0) -> 0.13594518
B90: =B89+1 -> 5 | C90: =C89+365 -> 44285 | D90: 74227 | E90: =IFERROR(D90/D89-1,0) -> 0.17210397 | G90: =G89+1 -> 5 | H90: =H89+365 -> 44285 | I90: 5325 | J90: =IFERROR(I90/I89-1,0) -> 0.14936326 | L90: =L89+1 -> 5 | M90: =M89+365 -> 44285 | N90: 25835 | O90: =IFERROR(N90/N89-1,0) -> 0.18962103
B91: =B90+1 -> 6 | C91: =C90+365 -> 44650 | D91: 73252 | E91: =IFERROR(D91/D90-1,0) -> -0.013135382 | G91: =G90+1 -> 6 | H91: =H90+365 -> 44650 | I91: 5474 | J91: =IFERROR(I91/I90-1,0) -> 0.027981221 | L91: =L90+1 -> 6 | M91: =M90+365 -> 44650 | N91: 35905 | O91: =IFERROR(N91/N90-1,0) -> 0.3897813
B92: =B91+1 -> 7 | C92: =C91+365 -> 45015 | D92: 73338 | E92: =IFERROR(D92/D91-1,0) -> 0.0011740294 | G92: =G91+1 -> 7 | H92: =H91+365 -> 45015 | I92: 8299 | J92: =IFERROR(I92/I91-1,0) -> 0.516076 | L92: =L91+1 -> 7 | M92: =M91+365 -> 45015 | N92: 40890 | O92: =IFERROR(N92/N91-1,0) -> 0.1388386
B93: =B92+1 -> 8 | C93: =C92+365 -> 45380 | D93: 86045 | E93: =IFERROR(D93/D92-1,0) -> 0.17326625 | G93: =G92+1 -> 8 | H93: =H92+365 -> 45380 | I93: 8359 | J93: =IFERROR(I93/I92-1,0) -> 0.0072297867 | L93: =L92+1 -> 8 | M93: =M92+365 -> 45380 | N93: 39545 | O93: =IFERROR(N93/N92-1,0) -> -0.032893128
B94: =B93+1 -> 9 | C94: =C93+365 -> 45745 | D94: 93745 | E94: =IFERROR(D94/D93-1,0) -> 0.089488059 | G94: =G93+1 -> 9 | H94: =H93+365 -> 45745 | I94: 8227 | J94: =IFERROR(I94/I93-1,0) -> -0.015791363 | L94: =L93+1 -> 9 | M94: =M93+365 -> 45745 | N94: 43750 | O94: =IFERROR(N94/N93-1,0) -> 0.10633456
B95: =B94+1 -> 10 | C95: =C94+365 -> 46110 | D95: 90828 | E95: =IFERROR(D95/D94-1,0) -> -0.031116326 | G95: =G94+1 -> 10 | H95: =H94+365 -> 46110 | I95: 9176 | J95: =IFERROR(I95/I94-1,0) -> 0.11535189 | L95: =L94+1 -> 10 | M95: =M94+365 -> 46110 | N95: 52260 | O95: =IFERROR(N95/N94-1,0) -> 0.19451429
B96: =B95+1 -> 11 | C96: =C95+365 -> 46475 | D96: {=FORECAST(B96,$D$86:$D$95,$B$86:$B$95)} -> 93643.733 | E96: =IFERROR(D96/D95-1,0) -> 0.031000719 | G96: =G95+1 -> 11 | H96: =H95+365 -> 46475 | I96: {=FORECAST(G96,$I$86:$I$95,$G$86:$G$95)} -> 11386.467 | J96: =IFERROR(I96/I95-1,0) -> 0.24089654 | L96: =L95+1 -> 11 | M96: =M95+365 -> 46475 | N96: {=FORECAST(L96,$N$86:$N$95,$L$86:$L$95)} -> 54689.133 | O96: =IFERROR(N96/N95-1,0) -> 0.046481694
B97: =B96+1 -> 12 | C97: =C96+365 -> 46840 | D97: {=FORECAST(B97,$D$86:$D$95,$B$86:$B$95)} -> 97047.794 | E97: =IFERROR(D97/D96-1,0) -> 0.036351184 | G97: =G96+1 -> 12 | H97: =H96+365 -> 46840 | I97: {=FORECAST(G97,$I$86:$I$95,$G$86:$G$95)} -> 12556.861 | J97: =IFERROR(I97/I96-1,0) -> 0.10278816 | L97: =L96+1 -> 12 | M97: =M96+365 -> 46840 | N97: {=FORECAST(L97,$N$86:$N$95,$L$86:$L$95)} -> 59039.667 | O97: =IFERROR(N97/N96-1,0) -> 0.079550234
B98: =B97+1 -> 13 | C98: =C97+365 -> 47205 | D98: {=FORECAST(B98,$D$86:$D$95,$B$86:$B$95)} -> 100451.85 | E98: =IFERROR(D98/D97-1,0) -> 0.035076126 | G98: =G97+1 -> 13 | H98: =H97+365 -> 47205 | I98: {=FORECAST(G98,$I$86:$I$95,$G$86:$G$95)} -> 13727.255 | J98: =IFERROR(I98/I97-1,0) -> 0.093207528 | L98: =L97+1 -> 13 | M98: =M97+365 -> 47205 | N98: {=FORECAST(L98,$N$86:$N$95,$L$86:$L$95)} -> 63390.2 | O98: =IFERROR(N98/N97-1,0) -> 0.073688311
B99: =B98+1 -> 14 | C99: =C98+365 -> 47570 | D99: {=FORECAST(B99,$D$86:$D$95,$B$86:$B$95)} -> 103855.92 | E99: =IFERROR(D99/D98-1,0) -> 0.033887484 | G99: =G98+1 -> 14 | H99: =H98+365 -> 47570 | I99: {=FORECAST(G99,$I$86:$I$95,$G$86:$G$95)} -> 14897.648 | J99: =IFERROR(I99/I98-1,0) -> 0.085260599 | L99: =L98+1 -> 14 | M99: =M98+365 -> 47570 | N99: {=FORECAST(L99,$N$86:$N$95,$L$86:$L$95)} -> 67740.733 | O99: =IFERROR(N99/N98-1,0) -> 0.068631008
B100: =B99+1 -> 15 | C100: =C99+365 -> 47935 | D100: {=FORECAST(B100,$D$86:$D$95,$B$86:$B$95)} -> 107259.98 | E100: =IFERROR(D100/D99-1,0) -> 0.032776762 | G100: =G99+1 -> 15 | H100: =H99+365 -> 47935 | I100: {=FORECAST(G100,$I$86:$I$95,$G$86:$G$95)} -> 16068.042 | J100: =IFERROR(I100/I99-1,0) -> 0.078562328 | L100: =L99+1 -> 15 | M100: =M99+365 -> 47935 | N100: {=FORECAST(L100,$N$86:$N$95,$L$86:$L$95)} -> 72091.267 | O100: =IFERROR(N100/N99-1,0) -> 0.064223298
B103: FIXED ASSESTS NET BLOCK | G103: INVESTMENTS | L103: OTHER ASSESTS
B105: YEAR WEIGHT | C105: YEAR | D105: F.A.N.B | E105: F.A.N.B GROWTH | G105: YEAR WEIGHT | H105: YEAR | I105: INVESTMENTS | J105: INVESTMENTS GROWTH | L105: YEAR WEIGHT | M105: YEAR | N105: OTHER ASSESTS | O105: OTHER ASSESTS GROWTH
B106: 1 | C106: ='Data Sheet'!$B$16 -> 42825 | D106: {=TRANSPOSE('Balance Sheet'!B10:K10)} -> 14179 | G106: 1 | H106: ='Data Sheet'!$B$16 -> 42825 | I106: {=TRANSPOSE('Balance Sheet'!B12:K12)} -> 16423 | L106: 1 | M106: ='Data Sheet'!$B$16 -> 42825 | N106: {=TRANSPOSE('Balance Sheet'!B13:K13)} -> 16234
B107: =B106+1 -> 2 | C107: =C106+365 -> 43190 | D107: 12574 | E107: =IFERROR(D107/D106-1,0) -> -0.11319557 | G107: =G106+1 -> 2 | H107: =H106+365 -> 43190 | I107: 12163 | J107: =IFERROR(I107/I106-1,0) -> -0.25939232 | L107: =L106+1 -> 2 | M107: =M106+365 -> 43190 | N107: 20046 | O107: =IFERROR(N107/N106-1,0) -> 0.23481582
B108: =B107+1 -> 3 | C108: =C107+365 -> 43555 | D108: 15710 | E108: =IFERROR(D108/D107-1,0) -> 0.24940353 | G108: =G107+1 -> 3 | H108: =H107+365 -> 43555 | I108: 11261 | J108: =IFERROR(I108/I107-1,0) -> -0.074159336 | L108: =L107+1 -> 3 | M108: =M107+365 -> 43555 | N108: 21312 | O108: =IFERROR(N108/N107-1,0) -> 0.063154744
B109: =B108+1 -> 4 | C109: =C108+365 -> 43920 | D109: 23789 | E109: =IFERROR(D109/D108-1,0) -> 0.51425843 | G109: =G108+1 -> 4 | H109: =H108+365 -> 43920 | I109: 8792 | J109: =IFERROR(I109/I108-1,0) -> -0.21925229 | L109: =L108+1 -> 4 | M109: =M108+365 -> 43920 | N109: 21129 | O109: =IFERROR(N109/N108-1,0) -> -0.0085867117
B110: =B109+1 -> 5 | C110: =C109+365 -> 44285 | D110: 25505 | E110: =IFERROR(D110/D109-1,0) -> 0.07213418 | G110: =G109+1 -> 5 | H110: =H109+365 -> 44285 | I110: 14205 | J110: =IFERROR(I110/I109-1,0) -> 0.61567334 | L110: =L109+1 -> 5 | M110: =M109+365 -> 44285 | N110: 22871 | O110: =IFERROR(N110/N109-1,0) -> 0.082445927
B111: =B110+1 -> 6 | C111: =C110+365 -> 44650 | D111: 25800 | E111: =IFERROR(D111/D110-1,0) -> 0.01156636 | G111: =G110+1 -> 6 | H111: =H110+365 -> 44650 | I111: 20324 | J111: =IFERROR(I111/I110-1,0) -> 0.43076382 | L111: =L110+1 -> 6 | M111: =M110+365 -> 44650 | N111: 30019 | O111: =IFERROR(N111/N110-1,0) -> 0.31253553
B112: =B111+1 -> 7 | C112: =C111+365 -> 45015 | D112: 29225 | E112: =IFERROR(D112/D111-1,0) -> 0.13275194 | G112: =G111+1 -> 7 | H112: =H111+365 -> 45015 | I112: 19478 | J112: =IFERROR(I112/I111-1,0) -> -0.041625664 | L112: =L111+1 -> 7 | M112: =M111+365 -> 45015 | N112: 38008 | O112: =IFERROR(N112/N111-1,0) -> 0.26613145
B113: =B112+1 -> 8 | C113: =C112+365 -> 45380 | D113: 27622 | E113: =IFERROR(D113/D112-1,0) -> -0.054850299 | G113: =G112+1 -> 8 | H113: =H112+365 -> 45380 | I113: 24623 | J113: =IFERROR(I113/I112-1,0) -> 0.26414416 | L113: =L112+1 -> 8 | M113: =M112+365 -> 45380 | N113: 38503 | O113: =IFERROR(N113/N112-1,0) -> 0.013023574
B114: =B113+1 -> 9 | C114: =C113+365 -> 45745 | D114: 30961 | E114: =IFERROR(D114/D113-1,0) -> 0.12088191 | G114: =G113+1 -> 9 | H114: =H113+365 -> 45745 | I114: 23541 | J114: =IFERROR(I114/I113-1,0) -> -0.043942655 | L114: =L113+1 -> 9 | M114: =M113+365 -> 45745 | N114: 36866 | O114: =IFERROR(N114/N113-1,0) -> -0.042516168
B115: =B114+1 -> 10 | C115: =C114+365 -> 46110 | D115: 33770 | E115: =IFERROR(D115/D114-1,0) -> 0.090727044 | G115: =G114+1 -> 10 | H115: =H114+365 -> 46110 | I115: 21880 | J115: =IFERROR(I115/I114-1,0) -> -0.07055775 | L115: =L114+1 -> 10 | M115: =M114+365 -> 46110 | N115: 40677 | O115: =IFERROR(N115/N114-1,0) -> 0.10337438
B116: =B115+1 -> 11 | C116: =C115+365 -> 46475 | D116: {=FORECAST(B116,$D$106:$D$115,$B$106:$B$115)} -> 36619.867 | E116: =IFERROR(D116/D115-1,0) -> 0.084390485 | G116: =G115+1 -> 11 | H116: =H115+365 -> 46475 | I116: {=FORECAST(G116,$I$106:$I$115,$G$106:$G$115)} -> 25060.533 | J116: =IFERROR(I116/I115-1,0) -> 0.14536258 | L116: =L115+1 -> 11 | M116: =M115+365 -> 46475 | N116: {=FORECAST(L116,$N$106:$N$115,$L$106:$L$115)} -> 44615.4 | O116: =IFERROR(N116/N115-1,0) -> 0.0968213
B117: =B116+1 -> 12 | C117: =C116+365 -> 46840 | D117: {=FORECAST(B117,$D$106:$D$115,$B$106:$B$115)} -> 38930.115 | E117: =IFERROR(D117/D116-1,0) -> 0.063087299 | G117: =G116+1 -> 12 | H117: =H116+365 -> 46840 | I117: {=FORECAST(G117,$I$106:$I$115,$G$106:$G$115)} -> 26477.176 | J117: =IFERROR(I117/I116-1,0) -> 0.056528822 | L117: =L116+1 -> 12 | M117: =M116+365 -> 46840 | N117: {=FORECAST(L117,$N$106:$N$115,$L$106:$L$115)} -> 47533.382 | O117: =IFERROR(N117/N116-1,0) -> 0.065403018
B118: =B117+1 -> 13 | C118: =C117+365 -> 47205 | D118: {=FORECAST(B118,$D$106:$D$115,$B$106:$B$115)} -> 41240.364 | E118: =IFERROR(D118/D117-1,0) -> 0.059343479 | G118: =G117+1 -> 13 | H118: =H117+365 -> 47205 | I118: {=FORECAST(G118,$I$106:$I$115,$G$106:$G$115)} -> 27893.818 | J118: =IFERROR(I118/I117-1,0) -> 0.053504288 | L118: =L117+1 -> 13 | M118: =M117+365 -> 47205 | N118: {=FORECAST(L118,$N$106:$N$115,$L$106:$L$115)} -> 50451.364 | O118: =IFERROR(N118/N117-1,0) -> 0.061388054
...

Sheet DCF VALUATION<

Sheet WACC
A3: # | B3: Weighted Average Cost of Capital (WACC)
B5: All figures are in INR unless stated otherwise.
B7: Peer Comps
G8: Debt/ | H8: Debt/ | I8: Levered | J8: Unlevered
B9: Name | C9: Country | D9: Total Debt | E9: Total Equity | F9: Tax Rate 1 | G9: Equity | H9: Capital | I9: Beta 2 | J9: Beta 3
B10: 1 | C10: TCS | D10: 11283 | E10: 744077.8 | F10: 0.27 | G10: =IFERROR(D10/E10,0) -> 0.015163737 | H10: =IFERROR(D10/(D10+E10),0) -> 0.014937233 | I10: 0.24 | J10: =I10/(1+(1-F10)*G10) -> 0.2373724
B11: 2 | C11: ='Data Sheet'!B1 -> INFOSYS LTD | D11: 9176 | E11: 421825.86 | F11: 0.27 | G11: =IFERROR(D11/E11,0) -> 0.021753052 | H11: =IFERROR(D11/(D11+E11),0) -> 0.021289931 | I11: 0.68 | J11: =I11/(1+(1-F11)*G11) -> 0.66937058
B12: 3 | C12: HCL TECHNOLOGIES | D12: 5215 | E12: 307105.46 | F12: 0.27 | G12: =IFERROR(D12/E12,0) -> 0.016981137 | H12: =IFERROR(D12/(D12+E12),0) -> 0.016697593 | I12: 0.8 | J12: =I12/(1+(1-F12)*G12) -> 0.79020444
B13: 4 | C13: WIPRO | D13: 20291 | E13: 172569.32 | F13: 0.27 | G13: =IFERROR(D13/E13,0) -> 0.11758173 | H13: =IFERROR(D13/(D13+E13),0) -> 0.10521086 | I13: 0.38 | J13: =I13/(1+(1-F13)*G13) -> 0.3499612
B14: 5 | C14: TECH MAHINDRA | D14: 2186.2 | E14: 137761.79 | F14: 0.27 | G14: =IFERROR(D14/E14,0) -> 0.015869422 | H14: =IFERROR(D14/(D14+E14),0) -> 0.015621518 | I14: 0.6 | J14: =I14/(1+(1-F14)*G14) -> 0.59312879
E17: Average | F17: =AVERAGE(F10:F14) -> 0.27 | G17: =AVERAGE(G10:G14) -> 0.037469817 | H17: =AVERAGE(H10:H14) -> 0.034751427 | I17: =AVERAGE(I10:I14) -> 0.54 | J17: =AVERAGE(J10:J14) -> 0.52800748
E18: Median | F18: =MEDIAN(F11:F15) -> 0.27 | G18: =MEDIAN(G11:G15) -> 0.019367095 | H18: =MEDIAN(H11:H15) -> 0.018993762 | I18: =MEDIAN(I11:I15) -> 0.64 | J18: =MEDIAN(J11:J15) -> 0.63124969
B21: Cost of Debt | G21: Cost of Equity
B23: Pre-tax Cost of Debt | E23: ='Profit & Loss'!K16/WACC!D11 -> 0.045335658 | G23: Risk Free Rate | J23: 0.0675
B24: Tax Rate | E24: 0.27 | G24: Equity Risk Premium | J24: =J23-5.73% -> 0.0102
B25: After Tax Cost of Debt | E25: =E23*(1-E24) -> 0.033095031 | G25: Levered Beta 4 | J25: =J34 -> 0.65753156
G26: Cost of Equity | J26: =J23+(J24*J25) -> 0.074206822
B29: Capital Structure | G29: Levered Beta
D31: Current | E31: Target | G31: Comps Median Unlevered Beta | J31: =J18 -> 0.63124969
B32: Total Debt | C32: =D11 -> 9176 | D32: =C32/$C$34 -> 0.021289931 | E32: =H17 -> 0.034751427 | G32: Target Debt/ Equity | J32: =E36 -> 0.036002567
B33: Market Capitalization | C33: =E11 -> 421825.86 | D33: =C33/$C$34 -> 0.97871007 | E33: =E34-E32 -> 0.96524857 | G33: Tax Rate | J33: =F11 -> 0.27
B34: Total Capitalization | C34: =C32+C33 -> 431001.86 | D34: =C34/$C$34 -> 1 | E34: =D34 -> 1 | G34: Levered Beta | J34: =J31/1+(1-J33)*J32 -> 0.65753156
B36: Debt / Equity | D36: =D32/D33 -> 0.021753052 | E36: =E32/E33 -> 0.036002567 | G36: Weighted Average Cost of Capital
B38: 1. Tax Rate considered as Marginal Tax Rate for the country | G38: Cost of Equity | J38: =J26 -> 0.074206822
B39: 2. Levered Beta is based on 5 year monthly data | G39: Equity Weight | J39: =E33 -> 0.96524857
B40: 3. Unlevered Beta = Levered Beta/(1+(1-Tax Rate) x Debt/Equity)
B41: 3. Levered Beta = Unlevered Beta/(1+(1-Tax Rate) x Debt/Equity) | G41: Cost of Debt | J41: =E25 -> 0.033095031
G42: Debt Weight | J42: =E32 -> 0.034751427
G44: WACC | J44: =SUMPRODUCT(J38:J39,J41:J42) -> 0.035999642

Sheet DATA<

Sheet INTRINSIC GROWTH
B3: Calculation of ROIC | G3: =Annual[[#This Row],[Column7]] -> 44651 | H3: =Annual[[#This Row],[Column8]] -> 45016 | I3: =Annual[[#This Row],[Column9]] -> 45382 | J3: =Annual[[#This Row],[Column10]] -> 45747 | K3: =Annual[[#This Row],[Column11]] -> 46112
B5: Current Assets
B6: Inventories | G6: 0 | H6: 0 | I6: 0 | J6: 0 | K6: 0
B7: Trade receivables | G7: ='RAW FS'!E31 -> 22698 | H7: ='RAW FS'!F31 -> 25424 | I7: ='RAW FS'!G31 -> 30193 | J7: ='RAW FS'!H31 -> 31158 | K7: ='RAW FS'!I31 -> 35234
B8: Loans n Advances | G8: ='RAW FS'!E33 -> 2491 | H8: ='RAW FS'!F33 -> 3242 | I8: ='RAW FS'!G33 -> 10330 | J8: ='RAW FS'!H33 -> 6717 | K8: ='RAW FS'!I33 -> 6808
B9: Other asset items | G9: ='RAW FS'!E34 -> 27528 | H9: ='RAW FS'!F34 -> 34766 | I9: ='RAW FS'!G34 -> 28173 | J9: ='RAW FS'!H34 -> 30149 | K9: ='RAW FS'!I34 -> 33869
B10: Total Current Assets | G10: =SUM(G6:G9) -> 52717 | H10: =SUM(H6:H9) -> 63432 | I10: =SUM(I6:I9) -> 68696 | J10: =SUM(J6:J9) -> 68024 | K10: =SUM(K6:K9) -> 75911
B12: Current Liabilities
B13: Trade Payables | G13: ='RAW FS'!E12 -> 4134 | H13: ='RAW FS'!F12 -> 3865 | I13: ='RAW FS'!G12 -> 3956 | J13: ='RAW FS'!H12 -> 4164 | K13: ='RAW FS'!I12 -> 4744
B14: Advance From Customers | G14: ='RAW FS'!E13 -> 0 | H14: ='RAW FS'!F13 -> 0 | I14: ='RAW FS'!G13 -> 0 | J14: ='RAW FS'!H13 -> 0 | K14: ='RAW FS'!I13 -> 0
B15: Other liability items | G15: ='RAW FS'!E14 -> 31385 | H15: ='RAW FS'!F14 -> 36637 | I15: ='RAW FS'!G14 -> 35244 | J15: ='RAW FS'!H14 -> 39201 | K15: ='RAW FS'!I14 -> 47071
B16: Total Current Liabilities | G16: =SUM(G13:G15) -> 35519 | H16: =SUM(H13:H15) -> 40502 | I16: =SUM(I13:I15) -> 39200 | J16: =SUM(J13:J15) -> 43365 | K16: =SUM(K13:K15) -> 51815
B18: Net Working Capital | G18: =G10-G16 -> 17198 | H18: =H10-H16 -> 22930 | I18: =I10-I16 -> 29496 | J18: =J10-J16 -> 24659 | K18: =K10-K16 -> 24096
B20: Non Current Assets
B21: Land | G21: ='RAW FS'!E17 -> 2066 | H21: ='RAW FS'!F17 -> 2054 | I21: ='RAW FS'!G17 -> 2037 | J21: ='RAW FS'!H17 -> 2079 | K21: ='RAW FS'!I17 -> 1990
B22: Building | G22: ='RAW FS'!E18 -> 16760 | H22: ='RAW FS'!F18 -> 16903 | I22: ='RAW FS'!G18 -> 16515 | J22: ='RAW FS'!H18 -> 16376 | K22: ='RAW FS'!I18 -> 17193
B23: Plant Machinery | G23: ='RAW FS'!E19 -> 3210 | H23: ='RAW FS'!F19 -> 3302 | I23: ='RAW FS'!G19 -> 3428 | J23: ='RAW FS'!H19 -> 3461 | K23: ='RAW FS'!I19 -> 3714
B24: Equipments | G24: ='RAW FS'!E20 -> 1427 | H24: ='RAW FS'!F20 -> 1482 | I24: ='RAW FS'!G20 -> 1528 | J24: ='RAW FS'!H20 -> 1628 | K24: ='RAW FS'!I20 -> 1732
B25: Customers | G25: ='RAW FS'!E21 -> 9936 | H25: ='RAW FS'!F21 -> 11898 | I25: ='RAW FS'!G21 -> 12353 | J25: ='RAW FS'!H21 -> 12925 | K25: ='RAW FS'!I21 -> 13600
B26: Furniture n fittings | G26: ='RAW FS'!E22 -> 2278 | H26: ='RAW FS'!F22 -> 2303 | I26: ='RAW FS'!G22 -> 2326 | J26: ='RAW FS'!H22 -> 2340 | K26: ='RAW FS'!I22 -> 2438
B27: Vehicles | G27: ='RAW FS'!E23 -> 71 | H27: ='RAW FS'!F23 -> 60 | I27: ='RAW FS'!G23 -> 62 | J27: ='RAW FS'!H23 -> 72 | K27: ='RAW FS'!I23 -> 70
B28: Intangible Assets | G28: ='RAW FS'!E24 -> 6495 | H28: ='RAW FS'!F24 -> 7594 | I28: ='RAW FS'!G24 -> 7652 | J28: ='RAW FS'!H24 -> 10626 | K28: ='RAW FS'!I24 -> 12729
B29: Other fixed assets | G29: ='RAW FS'!E25 -> 2766 | H29: ='RAW FS'!F25 -> 3281 | I29: ='RAW FS'!G25 -> 3294 | J29: ='RAW FS'!H25 -> 5184 | K29: ='RAW FS'!I25 -> 6296
B31: Gross Block | G31: =SUM(G21:G29) -> 45009 | H31: =SUM(H21:H29) -> 48877 | I31: =SUM(I21:I29) -> 49195 | J31: =SUM(J21:J29) -> 54691 | K31: =SUM(K21:K29) -> 59762
B32: Accumulated Depreciation | G32: ='RAW FS'!E27 -> 19209 | H32: ='RAW FS'!F27 -> 19652 | I32: ='RAW FS'!G27 -> 21573 | J32: ='RAW FS'!H27 -> 23730 | K32: ='RAW FS'!I27 -> 25992
B33: Net Non Current Assets | G33: =SUM(G31:G32) -> 64218 | H33: =SUM(H31:H32) -> 68529 | I33: =SUM(I31:I32) -> 70768 | J33: =SUM(J31:J32) -> 78421 | K33: =SUM(K31:K32) -> 85754
B35: Invested Capital | G35: =G18+G33 -> 81416 | H35: =H18+H33 -> 91459 | I35: =I18+I33 -> 100264 | J35: =J18+J33 -> 103080 | K35: =K18+K33 -> 109850
B36: EBIT | G36: ='Profit & Loss'!G18+'Profit & Loss'!G16 -> 30310 | H36: ='Profit & Loss'!H18+'Profit & Loss'!H16 -> 33606 | I36: ='Profit & Loss'!I18+'Profit & Loss'!I16 -> 36458 | J36: ='Profit & Loss'!J18+'Profit & Loss'!J16 -> 38024 | K36: ='Profit & Loss'!K18+'Profit & Loss'!K16 -> 40411
B38: ROIC | G38: =G36/G35 -> 0.37228555 | H38: =H36/H35 -> 0.36744334 | I38: =I36/I35 -> 0.36362004 | J38: =J36/J35 -> 0.36887854 | K38: =K36/K35 -> 0.36787437
B41: Calculation of Reinvestment Rate
B43: Net Capex | G43: ='RAW FS'!K49 -> -2161 | H43: ='RAW FS'!L49 -> -2579 | I43: ='RAW FS'!M49 -> -2201 | J43: ='RAW FS'!N49 -> -2237 | K43: ='RAW FS'!O49 -> -2727
B44: Change in Working Capital | H44: =H43-G43 -> -418 | I44: =I43-H43 -> 378 | J44: =J43-I43 -> -36 | K44: =K43-J43 -> -490
B46: EBIT | G46: =G36 -> 30310 | H46: =H36 -> 33606 | I46: =I36 -> 36458 | J46: =J36 -> 38024 | K46: =K36 -> 40411
B47: Marginal Tax Rate | G47: 0.25 | H47: 0.25 | I47: 0.25 | J47: 0.25 | K47: 0.25
B48: EBIT(1-T) | G48: =G46*(1-G47) -> 22732.5 | H48: =H46*(1-H47) -> 25204.5 | I48: =I46*(1-I47) -> 27343.5 | J48: =J46*(1-J47) -> 28518 | K48: =K46*(1-K47) -> 30308.25
B50: Reinvestment | H50: =SUM(H43:H44) -> -2997 | I50: =SUM(I43:I44) -> -1823 | J50: =SUM(J43:J44) -> -2273 | K50: =SUM(K43:K44) -> -3217
B52: Reinvestment Rate | H52: =H50/H48 -> -0.11890734 | I52: =I50/I48 -> -0.066670324 | J52: =J50/J48 -> -0.079704047 | K52: =K50/K48 -> -0.10614272
J54: 4 Year Average | K54: =AVERAGE(H52:K52) -> -0.092856106
J55: 4 Year Median | K55: =MEDIAN(H52:K52) -> -0.092923382
B57: Calculation of Growth Rate | G57: =G3 -> 44651 | H57: =H3 -> 45016 | I57: =I3 -> 45382 | J57: =J3 -> 45747 | K57: =K3 -> 46112
B59: Reinvestment Rate | H59: =H52 -> -0.11890734 | I59: =I52 -> -0.066670324 | J59: =J52 -> -0.079704047 | K59: =K52 -> -0.10614272
B60: ROIC | H60: =H38 -> 0.36744334 | I60: =I38 -> 0.36362004 | J60: =J38 -> 0.36887854 | K60: =K38 -> 0.36787437
B62: Intrinsic Growth | H62: =H59*H60 -> -0.043691709 | I62: =I59*I60 -> -0.024242666 | J62: =J59*J60 -> -0.029401112 | K62: =K59*K60 -> -0.039047186
J64: 4 Year Average | K64: =AVERAGE(H62:K62) -> -0.034095668
J65: 4 Year Median | K65: =MEDIAN(H62:K62) -> -0.034224149

Sheet RAW FS
B4: Corporate actions
E5: 44621 | F5: 44986 | G5: 45352 | H5: 45717 | I5: 46082
B6: Equity Capital | E6: 2098 | F6: 2069 | G6: 2071 | H6: 2073 | I6: 2024
B7: Reserves | E7: 73252 | F7: 73338 | G7: 86045 | H7: 93745 | I7: 90828
B8: Borrowings - | E8: 5474 | F8: 8299 | G8: 8359 | H8: 8227 | I8: 9176
B9: Lease Liabilities | E9: 5474 | F9: 8299 | G9: 8359 | H9: 8227 | I9: 9176
B10: Other Liabilities - | E10: 35905 | F10: 40890 | G10: 39545 | H10: 43750 | I10: 52260
B11: Non controlling int | E11: 386 | F11: 388 | G11: 345 | H11: 385 | I11: 445
B12: Trade Payables | E12: 4134 | F12: 3865 | G12: 3956 | H12: 4164 | I12: 4744
B13: Advance from Customers | E13: 0 | F13: 0 | G13: 0 | H13: 0 | I13: 0
B14: Other liability items | E14: 31385 | F14: 36637 | G14: 35244 | H14: 39201 | I14: 47071
B15: Total Liabilities | E15: 116729 | F15: 124596 | G15: 136020 | H15: 147795 | I15: 154288
B16: Fixed Assets - | E16: 25800 | F16: 29225 | G16: 27622 | H16: 30961 | I16: 33770
B17: Land | E17: 2066 | F17: 2054 | G17: 2037 | H17: 2079 | I17: 1990
... B35: Total Assets | E35: 116729 | F35: 124596 | G35: 136020 | H35: 147795 | I35: 154288
D39: 42064 | E39: 42430 | F39: 42795 | G39: 43160 | H39: 43525 | I39: 43891 | J39: 44256 | K39: 44621 | L39: 44986 | M39: 45352 | N39: 45717 | O39: 46082
C40: Cash from Operating Activity - | D40: 8353 | E40: 10028 | F40: 11531 | G40: 13218 | H40: 14841 | I40: 17003 | J40: 23224 | K40: 23885 | L40: 22467 | M40: 25210 | N40: 35694 | O40: 33986
C41: Profit from operations | D41: 15946 | E41: 17839 | F41: 19340 | G41: 19963 | H41: 22126 | I41: 23920 | J41: 28845 | K41: 32921 | L41: 37605 | M41: 39523 | N41: 41591 | O41: 45273
C42: Receivables | D42: -1475 | E42: -1654 | F42: -1743 | G42: -1523 | H42: -2881 | I42: -3861 | J42: -1835 | K42: -7937 | L42: -7076 | M42: -2667 | N42: -1769 | O42: -5177
C43: Payables | D43: 0 | E43: 242 | F43: -19 | G43: 328 | H43: 916 | I43: -373 | J43: -245 | K43: 1489 | L43: -279 | M43: 91 | N43: 176 | O43: -26
C44: Loans Advances | D44: -221 | E44: -1134 | F44: 0 | G44: 0 | H44: 0 | I44: 0 | J44: -534 | K44: -1914 | L44: -3108 | M44: -1172 | N44: -1024 | O44: -2645
C45: Other WC items | D45: 854 | E45: 600 | F45: -394 | G45: 1279 | H45: 1512 | I45: 1867 | J45: 3382 | K45: 6938 | L45: 4119 | M45: -1334 | N45: 2322 | O45: 5209
C46: Working capital changes | D46: -842 | E46: -1946 | F46: -2156 | G46: 84 | H46: -453 | I46: -2367 | J46: 768 | K46: -1424 | L46: -6344 | M46: -5082 | N46: -295 | O46: -2639
C47: Direct taxes | D47: -6751 | E47: -5865 | F47: -5653 | G47: -6829 | H47: -6832 | I47: -4550 | J47: -6389 | K47: -7612 | L47: -8794 | M47: -9231 | N47: -5602 | O47: -8648
C48: Cash from Investing Activity - | D48: 999 | E48: -885 | F48: -14664 | G48: 4533 | H48: -632 | I48: -331 | J48: -7373 | K48: -6485 | L48: -1071 | M48: -5093 | N48: -1864 | O48: 3546
C49: Fixed assets purchased | D49: -2247 | E49: -2723 | F49: -2760 | G49: -1998 | H49: -2445 | I49: -3307 | J49: -2107 | K49: -2161 | L49: -2579 | M49: -2201 | N49: -2237 | O49: -2727
C50: Investments purchased | D50: -23923 | E50: -24577 | F50: -66410 | G50: -69159 | H50: -79410 | I50: -37482 | J50: -46738 | K50: -59951 | L50: -75800 | M50: -78092 | N50: -82742 | O50: -82617
C51: Investments sold | D51: 25253 | E51: 24980 | F51: 52048 | G51: 74003 | H51: 78098 | I51: 38861 | J51: 40381 | K51: 57356 | L51: 76722 | M51: 72930 | N51: 84877 | O51: 89699
... C65: CFO/OP | D65: 1.01 | E65: 0.93 | F65: 0.92 | G65: 1.07 | H65: 1.07 | I65: 0.97 | J65: 1.06 | K65: 1 | L65: 0.89 | M65: 0.95 | N65: 1.05 | O65: 1.01

Sheet DCF
F3: 0 | G3: 0.5 | H3: 1.5 | I3: 2.5 | J3: 3.5 | K3: 4.5
B4: Calculation of PV of FCFF | F4: 46082 | G4: 46447 | H4: 46812 | I4: 47177 | J4: 47542 | K4: 47907
B6: EBIT | F6: ='Profit & Loss'!K14-'Profit & Loss'!K15 -> 40411 | G6: ='Profit & Loss'!L14-'Profit & Loss'!L15 -> 43016.333 | H6: ='Profit & Loss'!M14-'Profit & Loss'!M15 -> 45581.648 | I6: ='Profit & Loss'!N14-'Profit & Loss'!N15 -> 48146.964 | J6: ='Profit & Loss'!O14-'Profit & Loss'!O15 -> 50712.279 | K6: ='Profit & Loss'!P14-'Profit & Loss'!P15 -> 53277.594
B8: Tax Rate | F8: 0.25 | G8: =F8 -> 0.25 | H8: =G8 -> 0.25 | I8: =H8 -> 0.25 | J8: =I8 -> 0.25 | K8: =J8 -> 0.25
B10: EBIT (1-T) | F10: =F6*(1-F8) -> 30308.25 | G10: =G6*(1-G8) -> 32262.25 | H10: =H6*(1-H8) -> 34186.236 | I10: =I6*(1-I8) -> 36110.223 | J10: =J6*(1-J8) -> 38034.209 | K10: =K6*(1-K8) -> 39958.195
B12: Less: Reinvestment Rate | F12: ='INTRINSIC GROWTH'!K55 -> -0.092923382 | G12: =F12 -> -0.092923382 | H12: =G12 -> -0.092923382 | I12: =H12 -> -0.092923382 | J12: =I12 -> -0.092923382 | K12: =J12 -> -0.092923382
B14: Free Cash Flow to Firm | F14: =F10*(1-F12) -> 33124.595 | G14: =G10*(1-G12) -> 35260.167 | H14: =H10*(1-H12) -> 37362.937 | I14: =I10*(1-I12) -> 39465.707 | J14: =J10*(1-J12) -> 41568.476 | K14: =K10*(1-K12) -> 43671.246
B16: Discounting Factor | F16: =1/(1+$E$27)^F3 -> 1 | G16: =1/(1+$E$27)^G3 -> 0.98247203 | H16: =1/(1+$E$27)^H3 -> 0.94833241 | I16: =1/(1+$E$27)^I3 -> 0.91537909 | J16: =1/(1+$E$27)^J3 -> 0.88357085 | K16: =1/(1+$E$27)^K3 -> 0.85286791
B18: PV of FCFF
B20: Expected Growth | E20: =(AVERAGE('RATIO ANALYSIS'!M4:Q4)) -> 0.063768597
B21: Terminal Growth | E21: 0.035
B24: Calculation of Terminal Value | G24: SENSITIVITY ANALYSIS
G25: =E37 -> 30260510 | H25: 0.01 | I25: 0.02 | J25: 0.036 | K25: 0.0403
B26: FCFF (n+1) | E26: =F14*(1+E20) -> 35236.904 | G26: 0.035 | H26: -1150428.3 | I26: -1951519.5 | J26: 30249707 | K26: 5762879.7
B27: WACC | E27: =WACC!J44 -> 0.035999642 | G27: 0.04 | H27: -925802.19 | I27: -1414307.5 | J27: -7315766 | K27: 98522066
B28: Terminal Growth Rate | E28: =E21 -> 0.035 | G28: 0.0575 | H28: -512017.19 | I28: -662210.7 | J28: -1200456.5 | K28: -1517637.8
G29: 0.06 | H29: -476549.9 | I29: -608489.49 | J29: -1054853.9 | K29: -1300002.5
B30: Terminal Value | E30: =E26/(E27-E28) -> 35249516 | G30: 0.07 | H30: -364236.83 | I30: -447325.89 | J30: -686564.94 | K30: -795850.63
B33: Calculation of Enterprise Value
B35: PV of FCFF | E35: =SUM(G14:K14) -> 197328.53
B36: PV of Terminal Value | E36: =K16*E30 -> 30063181
B37: Value of Operating Asset | E37: =SUM(E35:E36) -> 30260510
B39: Add: Cash | E39: ='RAW FS'!I32 -> 22201
B40: Less: Debt | E40: ='RAW FS'!E8 -> 5474
B41: Value of Equity | E41: =E37+E39-E40 -> 30277237
B42: No. of Shares | E42: ='Data Sheet'!B6 -> 405.75785
B43: Value per Share | E43: =E41/E42 -> 74618.98

Sheet DATA ROOM<

Sheet Data Sheet
A1: COMPANY NAME | B1: INFOSYS LTD | E1: =IF(B2<>B3, "A NEW VERSION OF THE WORKSHEET IS AVAILABLE", "")
A2: LATEST VERSION | B2: 2.1 | E2: PLEASE DO NOT MAKE ANY CHANGES TO THIS SHEET
A3: CURRENT VERSION | B3: 2.1
A5: META
A6: Number of shares | B6: =IF(B9>0, B9/B8, 0) -> 405.75785
A7: Face Value | B7: 5
A8: Current Price | B8: 1034.05
A9: Market Capitalization | B9: 419573.9
A15: PROFIT & LOSS
A16: Report Date | B16: 42825 | C16: 43190 | D16: 43555 | E16: 43921 | F16: 44286 | G16: 44651 | H16: 45016 | I16: 45382 | J16: 45747 | K16: 46112
A17: Sales | B17: 68484 | C17: 70522 | D17: 82675 | E17: 90791 | F17: 100472 | G17: 121641 | H17: 146767 | I17: 153670 | J17: 162990 | K17: 178650
A18: Raw Material Cost
A19: Change in Inventory
A20: Power and Fuel | B20: 228 | C20: 207 | D20: 221 | E20: 229 | F20: 143 | G20: 132 | H20: 176 | I20: 199 | J20: 222 | K20: 223
A21: Other Mfr. Exp | B21: 6712 | C21: 7286 | D21: 9902 | E21: 11086 | F21: 12800 | G21: 20690 | H21: 26330 | I21: 27195 | J21: 30395 | K21: 32922
A22: Employee Cost | B22: 37669 | C22: 38902 | D22: 45323 | E22: 50895 | F22: 55547 | G22: 63997 | H22: 78374 | I22: 82636 | J22: 85968 | K22: 95112
A23: Selling and admin | B23: 4584 | C23: 4585 | D23: 5553 | E23: 5375 | F23: 3194 | G23: 4305 | H23: 5300 | I23: 5705 | J23: 6039 | K23: 6784
A24: Other Expenses | B24: 687 | C24: 720 | D24: 1506 | E24: 939 | F24: 899 | G24: 1026 | H24: 1457 | I24: 1510 | J24: 1130 | K24: 1329
A25: Other Income | B25: 3050 | C25: 3311 | D25: 2882 | E25: 2803 | F25: 2201 | G25: 2295 | H25: 2701 | I25: 4711 | J25: 3600 | K25: 3033
A26: Depreciation | B26: 1703 | C26: 1863 | D26: 2011 | E26: 2893 | F26: 3267 | G26: 3476 | H26: 4225 | I26: 4678 | J26: 4812 | K26: 4902
A27: Interest | E27: 170 | F27: 195 | G27: 200 | H27: 284 | I27: 470 | J27: 416 | K27: 416
A28: Profit before tax | B28: 19951 | C28: 20270 | D28: 21041 | E28: 22007 | F28: 26628 | G28: 30110 | H28: 33322 | I28: 35988 | J28: 37608 | K28: 39995
A29: Tax | B29: 5598 | C29: 4241 | D29: 5631 | E29: 5368 | F29: 7205 | G29: 7964 | H29: 9214 | I29: 9740 | J29: 10858 | K29: 10521
A30: Net profit | B30: 14353 | C30: 16029 | D30: 15404 | E30: 16594 | F30: 19351 | G30: 22110 | H30: 24095 | I30: 26233 | J30: 26713 | K30: 29440
A31: Dividend Amount | B31: 5891.6 | C31: 9465.6 | D31: 9222.5 | E31: 7427 | F31: 11469.6 | G31: 13007.6 | H31: 14069.2 | I31: 19053.2 | J31: 17827.8 | K31: 19430.4
A40: Quarters
A41: Report Date | B41: 45291 | C41: 45382 | D41: 45473 | E41: 45565 | F41: 45657 | G41: 45747 | H41: 45838 | I41: 45930 | J41: 46022 | K41: 46112
A42: Sales | B42: 38821 | C42: 37923 | D42: 39315 | E42: 40986 | F42: 41764 | G42: 40925 | H42: 42279 | I42: 44490 | J42: 45479 | K42: 46402
A43: Expenses | B43: 29684 | C43: 29139 | D43: 29878 | E43: 31177 | F43: 31649 | G43: 31051 | H43: 32336 | I43: 33955 | J43: 34845 | K43: 35235
A44: Other Income | B44: 789 | C44: 2729 | D44: 838 | E44: 712 | F44: 859 | G44: 1190 | H44: 1042 | I44: 982 | J44: -150 | K44: 1159
A45: Depreciation | B45: 1176 | C45: 1163 | D45: 1149 | E45: 1160 | F45: 1203 | G45: 1299 | H45: 1140 | I45: 1182 | J45: 1155 | K45: 1424
A46: Interest | B46: 131 | C46: 110 | D46: 105 | E46: 108 | F46: 101 | G46: 102 | H46: 105 | I46: 106 | J46: 100 | K46: 105
A47: Profit before tax | B47: 8619 | C47: 10240 | D47: 9021 | E47: 9253 | F47: 9670 | G47: 9663 | H47: 9740 | I47: 10229 | J47: 9229 | K47: 10797
A48: Tax | B48: 2506 | C48: 2265 | D48: 2647 | E48: 2737 | F48: 2848 | G48: 2625 | H48: 2816 | I48: 2854 | J48: 2563 | K48: 2288
A49: Net profit | B49: 6106 | C49: 7969 | D49: 6368 | E49: 6506 | F49: 6806 | G49: 7033 | H49: 6921 | I49: 7364 | J49: 6654 | K49: 8501
A50: Operating Profit | B50: 9137 | C50: 8784 | D50: 9437 | E50: 9809 | F50: 10115 | G50: 9874 | H50: 9943 | I50: 10535 | J50: 10634 | K50: 11167
A55: BALANCE SHEET
A56: Report Date | B56: 42825 | C56: 43190 | D56: 43555 | E56: 43921 | F56: 44286 | G56: 44651 | H56: 45016 | I56: 45382 | J56: 45747 | K56: 46112
A57: Equity Share Capital | B57: 1144 | C57: 1088 | D57: 2170 | E57: 2122 | F57: 2124 | G57: 2098 | H57: 2069 | I57: 2071 | J57: 2073 | K57: 2024
A58: Reserves | B58: 67838 | C58: 63835 | D58: 62778 | E58: 63328 | F58: 74227 | G58: 73252 | H58: 73338 | I58: 86045 | J58: 93745 | K58: 90828
A59: Borrowings | E59: 4633 | F59: 5325 | G59: 5474 | H59: 8299 | I59: 8359 | J59: 8227 | K59: 9176
A60: Other Liabilities | B60: 14166 | C60: 14426 | D60: 19118 | E60: 21717 | F60: 25835 | G60: 35905 | H60: 40890 | I60: 39545 | J60: 43750 | K60: 52260
A61: Total | B61: 83148 | C61: 79349 | D61: 84066 | E61: 91800 | F61: 107511 | G61: 116729 | H61: 124596 | I61: 136020 | J61: 147795 | K61: 154288
A62: Net Block | B62: 14179 | C62: 12574 | D62: 15710 | E62: 23789 | F62: 25505 | G62: 25800 | H62: 29225 | I62: 27622 | J62: 30961 | K62: 33770
A63: Capital Work in Progress | B63: 1365 | C63: 1606 | D63: 1388 | E63: 954 | F63: 922 | G63: 416 | H63: 288 | I63: 293 | J63: 814 | K63: 526
A64: Investments | B64: 16423 | C64: 12163 | D64: 11261 | E64: 8792 | F64: 14205 | G64: 20324 | H64: 19478 | I64: 24623 | J64: 23541 | K64: 21880
A65: Other Assets | B65: 51181 | C65: 53006 | D65: 55707 | E65: 58265 | F65: 66879 | G65: 70189 | H65: 75605 | I65: 83482 | J65: 92479 | K65: 98112
A66: Total | B66: 83148 | C66: 79349 | D66: 84066 | E66: 91800 | F66: 107511 | G66: 116729 | H66: 124596 | I66: 136020 | J66: 147795 | K66: 154288
A67: Receivables | B67: 12322 | C67: 13142 | D67: 14827 | E67: 18487 | F67: 19294 | G67: 22698 | H67: 25424 | I67: 30193 | J67: 31158 | K67: 35234
A68: Inventory
A69: Cash & Bank | B69: 22625 | C69: 19818 | D69: 19568 | E69: 18649 | F69: 24714 | G69: 17472 | H69: 12173 | I69: 14786 | J69: 24455 | K69: 22201
A70: No. of Equity Shares | B70: 2285655150 | C70: 2173312301 | D70: 4335954462 | E70: 4240753210 | F70: 4245146114 | G70: 4193012929 | H70: 4136387925 | I70: 4139950635 | J70: 4143607528 | K70: 4046940812
A71: New Bonus Shares | D71: 2184191490
A72: Face value | B72: 5 | C72: 5 | D72: 5 | E72: 5 | F72: 5 | G72: 5 | H72: 5 | I72: 5 | J72: 5 | K72: 5
A80: CASH FLOW:
A81: Report Date | B81: 42825 | C81: 43190 | D81: 43555 | E81: 43921 | F81: 44286 | G81: 44651 | H81: 45016 | I81: 45382 | J81: 45747 | K81: 46112
A82: Cash from Operating Activity | B82: 11531 | C82: 13218 | D82: 14841 | E82: 17003 | F82: 23224 | G82: 23885 | H82: 22467 | I82: 25210 | J82: 35694 | K82: 33986
A83: Cash from Investing Activity | B83: -14664 | C83: 4533 | D83: -632 | E83: -331 | F83: -7373 | G83: -6485 | H83: -1071 | I83: -5093 | J83: -1864 | K83: 3546
A84: Cash from Financing Activity | B84: -6939 | C84: -20505 | D84: -14512 | E84: -17591 | F84: -9786 | G84: -24642 | H84: -26695 | I84: -17504 | J84: -24161 | K84: -39786
A85: Net Cash Flow | B85: -10072 | C85: -2754 | D85: -303 | E85: -919 | F85: 6065 | G85: -7242 | H85: -5299 | I85: 2613 | J85: 9669 | K85: -2254
A90: PRICE: | B90: 511.13 | C90: 565.9 | D90: 743.85 | E90: 641.5 | F90: 1368.05 | G90: 1906.85 | H90: 1427.95 | I90: 1498.05 | J90: 1570.65 | K90: 1250.6
A92: DERIVED:
A93: Adjusted Equity Shares in Cr | B93: 459.39 | C93: 436.82 | D93: 436.89 | E93: 425.9 | F93: 426.07 | G93: 420.67 | H93: 414.86 | I93: 415.09 | J93: 415.33 | K93: 405.56
